{"history_past":[{"id":5209,"season_name":"2013/14","element_code":37605,"start_cost":100,"end_cost":96,"total_points":137,"minutes":2141,"goals_scored":5,"assists":10,"clean_sheets":13,"goals_conceded":23,"own_goals":0,"penalties_saved":0,"penalties_missed":0,"yellow_cards":0,"red_cards":0,"saves":0,"bonus":18,"bps":162,"influence":"0.0","creativity":"0.0","threat":"0.0","ict_index":"0.0","ea_index":641,"season":8},{"id":5688,"season_name":"2014/15","element_code":37605,"start_cost":90,"end_cost":90,"total_points":103,"minutes":1857,"goals_scored":4,"assists":6,"clean_sheets":9,"goals_conceded":16,"own_goals":0,"penalties_saved":0,"penalties_missed":0,"yellow_cards":0,"red_cards":0,"saves":0,"bonus":13,"bps":511,"influence":"0.0","creativity":"0.0","threat":"0.0","ict_index":"0.0","ea_index":463,"season":9},{"id":6402,"season_name":"2015/16","element_code":37605,"start_cost":85,"end_cost":92,"total_points":200,"minutes":3036,"goals_scored":6,"assists":19,"clean_sheets":17,"goals_conceded":31,"own_goals":0,"penalties_saved":0,"penalties_missed":0,"yellow_cards":4,"red_cards":0,"saves":0,"bonus":30,"bps":861,"influence":"0.0","creativity":"0.0","threat":"0.0","ict_index":"0.0","ea_index":783,"season":10},{"id":7107,"season_name":"2016/17","element_code":37605,"start_cost":95,"end_cost":95,"total_points":167,"minutes":2841,"goals_scored":8,"assists":11,"clean_sheets":12,"goals_conceded":30,"own_goals":0,"penalties_saved":0,"penalties_missed":0,"yellow_cards":2,"red_cards":0,"saves":0,"bonus":19,"bps":729,"influence":"834.4","creativity":"1649.3","threat":"734.0","ict_index":"322.0","ea_index":0,"season":11},{"id":7785,"season_name":"2017/18","element_code":37605,"start_cost":95,"end_cost":93,"total_points":112,"minutes":2161,"goals_scored":4,"assists":9,"clean_sheets":8,"goals_conceded":36,"own_goals":0,"penalties_saved":0,"penalties_missed":0,"yellow_cards":4,"red_cards":0,"saves":0,"bonus":11,"bps":506,"influence":"640.6","creativity":"1287.5","threat":"555.0","ict_index":"248.6","ea_index":0,"season":12}],"fixtures_summary":[],"explain":[{"explain":{"minutes":{"points":0,"name":"Minutes played","value":0}},"fixture":{"id":372,"kickoff_time_formatted":"12 May 15:00","started":true,"event_day":1,"deadline_time":"2019-05-12T13:00:00Z","deadline_time_formatted":"12 May 14:00","stats":[{"goals_scored":{"a":[{"value":2,"element":23},{"value":1,"element":552}],"h":[{"value":1,"element":85}]}},{"assists":{"a":[{"value":2,"element":15}],"h":[{"value":1,"element":76}]}},{"own_goals":{"a":[],"h":[]}},{"penalties_saved":{"a":[],"h":[]}},{"penalties_missed":{"a":[],"h":[]}},{"yellow_cards":{"a":[{"value":1,"element":451}],"h":[{"value":1,"element":67},{"value":1,"element":69},{"value":1,"element":72},{"value":1,"element":82},{"value":1,"element":85}]}},{"red_cards":{"a":[],"h":[]}},{"saves":{"a":[{"value":3,"element":2}],"h":[{"value":3,"element":67}]}},{"bonus":{"a":[{"value":3,"element":23},{"value":2,"element":15},{"value":1,"element":552}],"h":[]}},{"bps":{"a":[{"value":47,"element":23},{"value":37,"element":15},{"value":24,"element":552},{"value":20,"element":16},{"value":19,"element":18},{"value":18,"element":5},{"value":18,"element":7},{"value":15,"element":2},{"value":15,"element":11},{"value":13,"element":3},{"value":12,"element":451},{"value":3,"element":10},{"value":1,"element":566}],"h":[{"value":22,"element":85},{"value":15,"element":70},{"value":15,"element":534},{"value":13,"element":69},{"value":13,"element":74},{"value":12,"element":76},{"value":11,"element":67},{"value":11,"element":80},{"value":9,"element":72},{"value":9,"element":78},{"value":6,"element":82},{"value":4,"element":87},{"value":3,"element":79},{"value":3,"element":590}]}}],"code":987963,"kickoff_time":"2019-05-12T14:00:00Z","team_h_score":1,"team_a_score":3,"finished":true,"minutes":90,"provisional_start_time":false,"finished_provisional":true,"event":38,"team_a":1,"team_h":4}}],"history_summary":[{"id":19949,"kickoff_time":"2019-04-28T11:00:00Z","kickoff_time_formatted":"28 Apr 12:00","team_h_score":3,"team_a_score":0,"was_home":false,"round":36,"total_points":0,"value":79,"transfers_balance":-3584,"selected":166225,"transfers_in":2300,"transfers_out":5884,"loaned_in":0,"loaned_out":0,"minutes":0,"goals_scored":0,"assists":0,"clean_sheets":0,"goals_conceded":0,"own_goals":0,"penalties_saved":0,"penalties_missed":0,"yellow_cards":0,"red_cards":0,"saves":0,"bonus":0,"bps":0,"influence":"0.0","creativity":"0.0","threat":"0.0","ict_index":"0.0","ea_index":0,"open_play_crosses":0,"big_chances_created":0,"clearances_blocks_interceptions":0,"recoveries":0,"key_passes":0,"tackles":0,"winning_goals":0,"attempted_passes":0,"completed_passes":0,"penalties_conceded":0,"big_chances_missed":0,"errors_leading_to_goal":0,"errors_leading_to_goal_attempt":0,"tackled":0,"offside":0,"target_missed":0,"fouls":0,"dribbles":0,"element":13,"fixture":355,"opponent_team":11},{"id":20564,"kickoff_time":"2019-05-05T15:30:00Z","kickoff_time_formatted":"05 May 16:30","team_h_score":1,"team_a_score":1,"was_home":true,"round":37,"total_points":2,"value":79,"transfers_balance":-6482,"selected":159888,"transfers_in":1349,"transfers_out":7831,"loaned_in":0,"loaned_out":0,"minutes":90,"goals_scored":0,"assists":0,"clean_sheets":0,"goals_conceded":1,"own_goals":0,"penalties_saved":0,"penalties_missed":0,"yellow_cards":0,"red_cards":0,"saves":0,"bonus":0,"bps":16,"influence":"15.8","creativity":"47.7","threat":"4.0","ict_index":"6.8","ea_index":0,"open_play_crosses":1,"big_chances_created":0,"clearances_blocks_interceptions":1,"recoveries":3,"key_passes":3,"tackles":0,"winning_goals":0,"attempted_passes":60,"completed_passes":55,"penalties_conceded":0,"big_chances_missed":0,"errors_leading_to_goal":0,"errors_leading_to_goal_attempt":0,"tackled":3,"offside":1,"target_missed":0,"fouls":0,"dribbles":3,"element":13,"fixture":361,"opponent_team":3},{"id":21180,"kickoff_time":"2019-05-12T14:00:00Z","kickoff_time_formatted":"12 May 15:00","team_h_score":1,"team_a_score":3,"was_home":false,"round":38,"total_points":0,"value":79,"transfers_balance":1434,"selected":162012,"transfers_in":4531,"transfers_out":3097,"loaned_in":0,"loaned_out":0,"minutes":0,"goals_scored":0,"assists":0,"clean_sheets":0,"goals_conceded":0,"own_goals":0,"penalties_saved":0,"penalties_missed":0,"yellow_cards":0,"red_cards":0,"saves":0,"bonus":0,"bps":0,"influence":"0.0","creativity":"0.0","threat":"0.0","ict_index":"0.0","ea_index":0,"open_play_crosses":0,"big_chances_created":0,"clearances_blocks_interceptions":0,"recoveries":0,"key_passes":0,"tackles":0,"winning_goals":0,"attempted_passes":0,"completed_passes":0,"penalties_conceded":0,"big_chances_missed":0,"errors_leading_to_goal":0,"errors_leading_to_goal_attempt":0,"tackled":0,"offside":0,"target_missed":0,"fouls":0,"dribbles":0,"element":13,"fixture":372,"opponent_team":4}],"fixtures":[],"history":[{"id":13,"kickoff_time":"2018-08-12T15:00:00Z","kickoff_time_formatted":"12 Aug 16:00","team_h_score":0,"team_a_score":2,"was_home":true,"round":1,"total_points":2,"value":85,"transfers_balance":0,"selected":236460,"transfers_in":0,"transfers_out":0,"loaned_in":0,"loaned_out":0,"minutes":90,"goals_scored":0,"assists":0,"clean_sheets":0,"goals_conceded":2,"own_goals":0,"penalties_saved":0,"penalties_missed":0,"yellow_cards":0,"red_cards":0,"saves":0,"bonus":0,"bps":10,"influence":"9.2","creativity":"24.7","threat":"6.0","ict_index":"4.0","ea_index":0,"open_play_crosses":0,"big_chances_created":0,"clearances_blocks_interceptions":0,"recoveries":7,"key_passes":2,"tackles":0,"winning_goals":0,"attempted_passes":37,"completed_passes":29,"penalties_conceded":0,"big_chances_missed":0,"errors_leading_to_goal":0,"errors_leading_to_goal_attempt":0,"tackled":1,"offside":2,"target_missed":0,"fouls":0,"dribbles":1,"element":13,"fixture":1,"opponent_team":13},{"id":538,"kickoff_time":"2018-08-18T16:30:00Z","kickoff_time_formatted":"18 Aug 17:30","team_h_score":3,"team_a_score":2,"was_home":false,"round":2,"total_points":2,"value":85,"transfers_balance":-29452,"selected":235965,"transfers_in":9231,"transfers_out":38683,"loaned_in":0,"loaned_out":0,"minutes":67,"goals_scored":0,"assists":0,"clean_sheets":0,"goals_conceded":2,"own_goals":0,"penalties_saved":0,"penalties_missed":0,"yellow_cards":0,"red_cards":0,"saves":0,"bonus":0,"bps":3,"influence":"1.0","creativity":"2.3","threat":"12.0","ict_index":"1.5","ea_index":0,"open_play_crosses":0,"big_chances_created":0,"clearances_blocks_interceptions":1,"recoveries":2,"key_passes":0,"tackles":0,"winning_goals":0,"attempted_passes":18,"completed_passes":15,"penalties_conceded":0,"big_chances_missed":0,"errors_leading_to_goal":0,"errors_leading_to_goal_attempt":0,"tackled":2,"offside":0,"target_missed":1,"fouls":0,"dribbles":0,"element":13,"fixture":14,"opponent_team":6},{"id":1065,"kickoff_time":"2018-08-25T14:00:00Z","kickoff_time_formatted":"25 Aug 15:00","team_h_score":3,"team_a_score":1,"was_home":true,"round":3,"total_points":0,"value":84,"transfers_balance":-41534,"selected":201485,"transfers_in":10515,"transfers_out":52049,"loaned_in":0,"loaned_out":0,"minutes":0,"goals_scored":0,"assists":0,"clean_sheets":0,"goals_conceded":0,"own_goals":0,"penalties_saved":0,"penalties_missed":0,"yellow_cards":0,"red_cards":0,"saves":0,"bonus":0,"bps":0,"influence":"0.0","creativity":"0.0","threat":"0.0","ict_index":"0.0","ea_index":0,"open_play_crosses":0,"big_chances_created":0,"clearances_blocks_interceptions":0,"recoveries":0,"key_passes":0,"tackles":0,"winning_goals":0,"attempted_passes":0,"completed_passes":0,"penalties_conceded":0,"big_chances_missed":0,"errors_leading_to_goal":0,"errors_leading_to_goal_attempt":0,"tackled":0,"offside":0,"target_missed":0,"fouls":0,"dribbles":0,"element":13,"fixture":21,"opponent_team":19},{"id":1596,"kickoff_time":"2018-09-02T12:30:00Z","kickoff_time_formatted":"02 Sep 13:30","team_h_score":2,"team_a_score":3,"was_home":false,"round":4,"total_points":2,"value":83,"transfers_balance":-46139,"selected":159335,"transfers_in":2760,"transfers_out":48899,"loaned_in":0,"loaned_out":0,"minutes":83,"goals_scored":0,"assists":0,"clean_sheets":0,"goals_conceded":2,"own_goals":0,"penalties_saved":0,"penalties_missed":0,"yellow_cards":0,"red_cards":0,"saves":0,"bonus":0,"bps":8,"influence":"9.0","creativity":"21.8","threat":"6.0","ict_index":"3.7","ea_index":0,"open_play_crosses":0,"big_chances_created":0,"clearances_blocks_interceptions":1,"recoveries":4,"key_passes":1,"tackles":0,"winning_goals":0,"attempted_passes":47,"completed_passes":39,"penalties_conceded":0,"big_chances_missed":0,"errors_leading_to_goal":0,"errors_leading_to_goal_attempt":0,"tackled":4,"offside":0,"target_missed":0,"fouls":1,"dribbles":1,"element":13,"fixture":33,"opponent_team":5},{"id":2133,"kickoff_time":"2018-09-15T14:00:00Z","kickoff_time_formatted":"15 Sep 15:00","team_h_score":1,"team_a_score":2,"was_home":false,"round":5,"total_points":10,"value":83,"transfers_balance":-14570,"selected":149837,"transfers_in":5554,"transfers_out":20124,"loaned_in":0,"loaned_out":0,"minutes":90,"goals_scored":1,"assists":0,"clean_sheets":0,"goals_conceded":1,"own_goals":0,"penalties_saved":0,"penalties_missed":0,"yellow_cards":0,"red_cards":0,"saves":0,"bonus":3,"bps":35,"influence":"44.0","creativity":"47.3","threat":"23.0","ict_index":"11.4","ea_index":0,"open_play_crosses":1,"big_chances_created":0,"clearances_blocks_interceptions":0,"recoveries":4,"key_passes":3,"tackles":0,"winning_goals":1,"attempted_passes":38,"completed_passes":34,"penalties_conceded":0,"big_chances_missed":0,"errors_leading_to_goal":0,"errors_leading_to_goal_attempt":0,"tackled":1,"offside":0,"target_missed":0,"fouls":1,"dribbles":1,"element":13,"fixture":46,"opponent_team":15},{"id":2670,"kickoff_time":"2018-09-23T15:00:00Z","kickoff_time_formatted":"23 Sep 16:00","team_h_score":2,"team_a_score":0,"was_home":true,"round":6,"total_points":3,"value":83,"transfers_balance":13763,"selected":168695,"transfers_in":20664,"transfers_out":6901,"loaned_in":0,"loaned_out":0,"minutes":90,"goals_scored":0,"assists":0,"clean_sheets":1,"goals_conceded":0,"own_goals":0,"penalties_saved":0,"penalties_missed":0,"yellow_cards":0,"red_cards":0,"saves":0,"bonus":0,"bps":10,"influence":"19.0","creativity":"26.8","threat":"8.0","ict_index":"5.4","ea_index":0,"open_play_crosses":0,"big_chances_created":0,"clearances_blocks_interceptions":2,"recoveries":2,"key_passes":2,"tackles":0,"winning_goals":0,"attempted_passes":38,"completed_passes":30,"penalties_conceded":0,"big_chances_missed":0,"errors_leading_to_goal":0,"errors_leading_to_goal_attempt":0,"tackled":2,"offside":0,"target_missed":0,"fouls":0,"dribbles":1,"element":13,"fixture":51,"opponent_team":8},{"id":3208,"kickoff_time":"2018-09-29T14:00:00Z","kickoff_time_formatted":"29 Sep 15:00","team_h_score":2,"team_a_score":0,"was_home":true,"round":7,"total_points":10,"value":83,"transfers_balance":3474,"selected":174948,"transfers_in":13529,"transfers_out":10055,"loaned_in":0,"loaned_out":0,"minutes":90,"goals_scored":1,"assists":0,"clean_sheets":1,"goals_conceded":0,"own_goals":0,"penalties_saved":0,"penalties_missed":0,"yellow_cards":0,"red_cards":0,"saves":0,"bonus":2,"bps":28,"influence":"42.2","creativity":"30.7","threat":"19.0","ict_index":"9.2","ea_index":0,"open_play_crosses":1,"big_chances_created":0,"clearances_blocks_interceptions":0,"recoveries":5,"key_passes":1,"tackles":0,"winning_goals":0,"attempted_passes":64,"completed_passes":57,"penalties_conceded":0,"big_chances_missed":0,"errors_leading_to_goal":0,"errors_leading_to_goal_attempt":0,"tackled":3,"offside":0,"target_missed":0,"fouls":0,"dribbles":0,"element":13,"fixture":61,"opponent_team":18},{"id":3747,"kickoff_time":"2018-10-07T11:00:00Z","kickoff_time_formatted":"07 Oct 12:00","team_h_score":1,"team_a_score":5,"was_home":false,"round":8,"total_points":0,"value":83,"transfers_balance":58989,"selected":243629,"transfers_in":65987,"transfers_out":6998,"loaned_in":0,"loaned_out":0,"minutes":0,"goals_scored":0,"assists":0,"clean_sheets":0,"goals_conceded":0,"own_goals":0,"penalties_saved":0,"penalties_missed":0,"yellow_cards":0,"red_cards":0,"saves":0,"bonus":0,"bps":0,"influence":"0.0","creativity":"0.0","threat":"0.0","ict_index":"0.0","ea_index":0,"open_play_crosses":0,"big_chances_created":0,"clearances_blocks_interceptions":0,"recoveries":0,"key_passes":0,"tackles":0,"winning_goals":0,"attempted_passes":0,"completed_passes":0,"penalties_conceded":0,"big_chances_missed":0,"errors_leading_to_goal":0,"errors_leading_to_goal_attempt":0,"tackled":0,"offside":0,"target_missed":0,"fouls":0,"dribbles":0,"element":13,"fixture":74,"opponent_team":9},{"id":4289,"kickoff_time":"2018-10-22T19:00:00Z","kickoff_time_formatted":"22 Oct 20:00","team_h_score":3,"team_a_score":1,"was_home":true,"round":9,"total_points":12,"value":83,"transfers_balance":-17711,"selected":223066,"transfers_in":21552,"transfers_out":39263,"loaned_in":0,"loaned_out":0,"minutes":79,"goals_scored":1,"assists":1,"clean_sheets":0,"goals_conceded":1,"own_goals":0,"penalties_saved":0,"penalties_missed":0,"yellow_cards":0,"red_cards":0,"saves":0,"bonus":2,"bps":50,"influence":"65.8","creativity":"54.9","threat":"21.0","ict_index":"14.2","ea_index":0,"open_play_crosses":0,"big_chances_created":2,"clearances_blocks_interceptions":0,"recoveries":2,"key_passes":4,"tackles":0,"winning_goals":0,"attempted_passes":67,"completed_passes":62,"penalties_conceded":0,"big_chances_missed":0,"errors_leading_to_goal":0,"errors_leading_to_goal_attempt":0,"tackled":1,"offside":0,"target_missed":0,"fouls":0,"dribbles":2,"element":13,"fixture":81,"opponent_team":11},{"id":4835,"kickoff_time":"2018-10-28T13:30:00Z","kickoff_time_formatted":"28 Oct 13:30","team_h_score":2,"team_a_score":2,"was_home":false,"round":10,"total_points":2,"value":84,"transfers_balance":166775,"selected":410002,"transfers_in":175970,"transfers_out":9195,"loaned_in":0,"loaned_out":0,"minutes":67,"goals_scored":0,"assists":0,"clean_sheets":0,"goals_conceded":1,"own_goals":0,"penalties_saved":0,"penalties_missed":0,"yellow_cards":0,"red_cards":0,"saves":0,"bonus":0,"bps":9,"influence":"7.4","creativity":"15.1","threat":"2.0","ict_index":"2.5","ea_index":0,"open_play_crosses":0,"big_chances_created":0,"clearances_blocks_interceptions":1,"recoveries":4,"key_passes":1,"tackles":0,"winning_goals":0,"attempted_passes":37,"completed_passes":33,"penalties_conceded":0,"big_chances_missed":0,"errors_leading_to_goal":0,"errors_leading_to_goal_attempt":0,"tackled":2,"offside":0,"target_missed":0,"fouls":1,"dribbles":0,"element":13,"fixture":93,"opponent_team":7},{"id":5383,"kickoff_time":"2018-11-03T17:30:00Z","kickoff_time_formatted":"03 Nov 17:30","team_h_score":1,"team_a_score":1,"was_home":true,"round":11,"total_points":2,"value":84,"transfers_balance":-59683,"selected":338057,"transfers_in":19957,"transfers_out":79640,"loaned_in":0,"loaned_out":0,"minutes":90,"goals_scored":0,"assists":0,"clean_sheets":0,"goals_conceded":1,"own_goals":0,"penalties_saved":0,"penalties_missed":0,"yellow_cards":0,"red_cards":0,"saves":0,"bonus":0,"bps":13,"influence":"13.8","creativity":"53.2","threat":"8.0","ict_index":"7.5","ea_index":0,"open_play_crosses":1,"big_chances_created":0,"clearances_blocks_interceptions":0,"recoveries":3,"key_passes":4,"tackles":0,"winning_goals":0,"attempted_passes":46,"completed_passes":39,"penalties_conceded":0,"big_chances_missed":0,"errors_leading_to_goal":0,"errors_leading_to_goal_attempt":0,"tackled":2,"offside":2,"target_missed":0,"fouls":0,"dribbles":1,"element":13,"fixture":101,"opponent_team":12},{"id":5933,"kickoff_time":"2018-11-11T16:30:00Z","kickoff_time_formatted":"11 Nov 16:30","team_h_score":1,"team_a_score":1,"was_home":true,"round":12,"total_points":1,"value":84,"transfers_balance":1854,"selected":348419,"transfers_in":35372,"transfers_out":33518,"loaned_in":0,"loaned_out":0,"minutes":74,"goals_scored":0,"assists":0,"clean_sheets":0,"goals_conceded":1,"own_goals":0,"penalties_saved":0,"penalties_missed":0,"yellow_cards":1,"red_cards":0,"saves":0,"bonus":0,"bps":14,"influence":"12.6","creativity":"29.2","threat":"2.0","ict_index":"4.4","ea_index":0,"open_play_crosses":0,"big_chances_created":0,"clearances_blocks_interceptions":0,"recoveries":3,"key_passes":2,"tackles":0,"winning_goals":0,"attempted_passes":80,"completed_passes":73,"penalties_conceded":0,"big_chances_missed":0,"errors_leading_to_goal":0,"errors_leading_to_goal_attempt":0,"tackled":0,"offside":0,"target_missed":0,"fouls":1,"dribbles":3,"element":13,"fixture":111,"opponent_team":20},{"id":6485,"kickoff_time":"2018-11-25T13:30:00Z","kickoff_time_formatted":"25 Nov 13:30","team_h_score":1,"team_a_score":2,"was_home":false,"round":13,"total_points":0,"value":83,"transfers_balance":-36940,"selected":313097,"transfers_in":12146,"transfers_out":49086,"loaned_in":0,"loaned_out":0,"minutes":0,"goals_scored":0,"assists":0,"clean_sheets":0,"goals_conceded":0,"own_goals":0,"penalties_saved":0,"penalties_missed":0,"yellow_cards":0,"red_cards":0,"saves":0,"bonus":0,"bps":0,"influence":"0.0","creativity":"0.0","threat":"0.0","ict_index":"0.0","ea_index":0,"open_play_crosses":0,"big_chances_created":0,"clearances_blocks_interceptions":0,"recoveries":0,"key_passes":0,"tackles":0,"winning_goals":0,"attempted_passes":0,"completed_passes":0,"penalties_conceded":0,"big_chances_missed":0,"errors_leading_to_goal":0,"errors_leading_to_goal_attempt":0,"tackled":0,"offside":0,"target_missed":0,"fouls":0,"dribbles":0,"element":13,"fixture":121,"opponent_team":2},{"id":7038,"kickoff_time":"2018-12-02T14:05:00Z","kickoff_time_formatted":"02 Dec 14:05","team_h_score":4,"team_a_score":2,"was_home":true,"round":14,"total_points":0,"value":83,"transfers_balance":-43978,"selected":269697,"transfers_in":2743,"transfers_out":46721,"loaned_in":0,"loaned_out":0,"minutes":0,"goals_scored":0,"assists":0,"clean_sheets":0,"goals_conceded":0,"own_goals":0,"penalties_saved":0,"penalties_missed":0,"yellow_cards":0,"red_cards":0,"saves":0,"bonus":0,"bps":0,"influence":"0.0","creativity":"0.0","threat":"0.0","ict_index":"0.0","ea_index":0,"open_play_crosses":0,"big_chances_created":0,"clearances_blocks_interceptions":0,"recoveries":0,"key_passes":0,"tackles":0,"winning_goals":0,"attempted_passes":0,"completed_passes":0,"penalties_conceded":0,"big_chances_missed":0,"errors_leading_to_goal":0,"errors_leading_to_goal_attempt":0,"tackled":0,"offside":0,"target_missed":0,"fouls":0,"dribbles":0,"element":13,"fixture":131,"opponent_team":17},{"id":7594,"kickoff_time":"2018-12-05T20:00:00Z","kickoff_time_formatted":"05 Dec 20:00","team_h_score":2,"team_a_score":2,"was_home":false,"round":15,"total_points":0,"value":82,"transfers_balance":-58522,"selected":211143,"transfers_in":833,"transfers_out":59355,"loaned_in":0,"loaned_out":0,"minutes":0,"goals_scored":0,"assists":0,"clean_sheets":0,"goals_conceded":0,"own_goals":0,"penalties_saved":0,"penalties_missed":0,"yellow_cards":0,"red_cards":0,"saves":0,"bonus":0,"bps":0,"influence":"0.0","creativity":"0.0","threat":"0.0","ict_index":"0.0","ea_index":0,"open_play_crosses":0,"big_chances_created":0,"clearances_blocks_interceptions":0,"recoveries":0,"key_passes":0,"tackles":0,"winning_goals":0,"attempted_passes":0,"completed_passes":0,"penalties_conceded":0,"big_chances_missed":0,"errors_leading_to_goal":0,"errors_leading_to_goal_attempt":0,"tackled":0,"offside":0,"target_missed":0,"fouls":0,"dribbles":0,"element":13,"fixture":145,"opponent_team":14},{"id":8152,"kickoff_time":"2018-12-08T15:00:00Z","kickoff_time_formatted":"08 Dec 15:00","team_h_score":1,"team_a_score":0,"was_home":true,"round":16,"total_points":0,"value":81,"transfers_balance":-28646,"selected":183661,"transfers_in":740,"transfers_out":29386,"loaned_in":0,"loaned_out":0,"minutes":0,"goals_scored":0,"assists":0,"clean_sheets":0,"goals_conceded":0,"own_goals":0,"penalties_saved":0,"penalties_missed":0,"yellow_cards":0,"red_cards":0,"saves":0,"bonus":0,"bps":0,"influence":"0.0","creativity":"0.0","threat":"0.0","ict_index":"0.0","ea_index":0,"open_play_crosses":0,"big_chances_created":0,"clearances_blocks_interceptions":0,"recoveries":0,"key_passes":0,"tackles":0,"winning_goals":0,"attempted_passes":0,"completed_passes":0,"penalties_conceded":0,"big_chances_missed":0,"errors_leading_to_goal":0,"errors_leading_to_goal_attempt":0,"tackled":0,"offside":0,"target_missed":0,"fouls":0,"dribbles":0,"element":13,"fixture":151,"opponent_team":10},{"id":8711,"kickoff_time":"2018-12-16T13:30:00Z","kickoff_time_formatted":"16 Dec 13:30","team_h_score":3,"team_a_score":2,"was_home":false,"round":17,"total_points":1,"value":81,"transfers_balance":-13422,"selected":171556,"transfers_in":2060,"transfers_out":15482,"loaned_in":0,"loaned_out":0,"minutes":20,"goals_scored":0,"assists":0,"clean_sheets":0,"goals_conceded":1,"own_goals":0,"penalties_saved":0,"penalties_missed":0,"yellow_cards":0,"red_cards":0,"saves":0,"bonus":0,"bps":5,"influence":"6.0","creativity":"33.7","threat":"2.0","ict_index":"4.2","ea_index":0,"open_play_crosses":1,"big_chances_created":0,"clearances_blocks_interceptions":0,"recoveries":2,"key_passes":2,"tackles":0,"winning_goals":0,"attempted_passes":12,"completed_passes":11,"penalties_conceded":0,"big_chances_missed":0,"errors_leading_to_goal":0,"errors_leading_to_goal_attempt":0,"tackled":0,"offside":0,"target_missed":0,"fouls":1,"dribbles":0,"element":13,"fixture":167,"opponent_team":16},{"id":9273,"kickoff_time":"2018-12-22T12:30:00Z","kickoff_time_formatted":"22 Dec 12:30","team_h_score":3,"team_a_score":1,"was_home":true,"round":18,"total_points":5,"value":81,"transfers_balance":-5015,"selected":167823,"transfers_in":1958,"transfers_out":6973,"loaned_in":0,"loaned_out":0,"minutes":90,"goals_scored":0,"assists":1,"clean_sheets":0,"goals_conceded":1,"own_goals":0,"penalties_saved":0,"penalties_missed":0,"yellow_cards":0,"red_cards":0,"saves":0,"bonus":0,"bps":21,"influence":"4.2","creativity":"9.1","threat":"20.0","ict_index":"3.3","ea_index":0,"open_play_crosses":0,"big_chances_created":0,"clearances_blocks_interceptions":0,"recoveries":3,"key_passes":0,"tackles":0,"winning_goals":0,"attempted_passes":50,"completed_passes":47,"penalties_conceded":0,"big_chances_missed":0,"errors_leading_to_goal":0,"errors_leading_to_goal_attempt":0,"tackled":2,"offside":0,"target_missed":0,"fouls":0,"dribbles":1,"element":13,"fixture":171,"opponent_team":4},{"id":9838,"kickoff_time":"2018-12-26T17:15:00Z","kickoff_time_formatted":"26 Dec 17:15","team_h_score":1,"team_a_score":1,"was_home":false,"round":19,"total_points":1,"value":80,"transfers_balance":89,"selected":169488,"transfers_in":4756,"transfers_out":4667,"loaned_in":0,"loaned_out":0,"minutes":45,"goals_scored":0,"assists":0,"clean_sheets":0,"goals_conceded":1,"own_goals":0,"penalties_saved":0,"penalties_missed":0,"yellow_cards":0,"red_cards":0,"saves":0,"bonus":0,"bps":3,"influence":"2.2","creativity":"14.2","threat":"4.0","ict_index":"2.0","ea_index":0,"open_play_crosses":0,"big_chances_created":0,"clearances_blocks_interceptions":0,"recoveries":2,"key_passes":1,"tackles":0,"winning_goals":0,"attempted_passes":26,"completed_passes":23,"penalties_conceded":0,"big_chances_missed":0,"errors_leading_to_goal":0,"errors_leading_to_goal_attempt":0,"tackled":1,"offside":0,"target_missed":0,"fouls":0,"dribbles":0,"element":13,"fixture":181,"opponent_team":3},{"id":10406,"kickoff_time":"2018-12-29T17:30:00Z","kickoff_time_formatted":"29 Dec 17:30","team_h_score":5,"team_a_score":1,"was_home":false,"round":20,"total_points":0,"value":80,"transfers_balance":-9277,"selected":160573,"transfers_in":1093,"transfers_out":10370,"loaned_in":0,"loaned_out":0,"minutes":0,"goals_scored":0,"assists":0,"clean_sheets":0,"goals_conceded":0,"own_goals":0,"penalties_saved":0,"penalties_missed":0,"yellow_cards":0,"red_cards":0,"saves":0,"bonus":0,"bps":0,"influence":"0.0","creativity":"0.0","threat":"0.0","ict_index":"0.0","ea_index":0,"open_play_crosses":0,"big_chances_created":0,"clearances_blocks_interceptions":0,"recoveries":0,"key_passes":0,"tackles":0,"winning_goals":0,"attempted_passes":0,"completed_passes":0,"penalties_conceded":0,"big_chances_missed":0,"errors_leading_to_goal":0,"errors_leading_to_goal_attempt":0,"tackled":0,"offside":0,"target_missed":0,"fouls":0,"dribbles":0,"element":13,"fixture":196,"opponent_team":12},{"id":10974,"kickoff_time":"2019-01-01T15:00:00Z","kickoff_time_formatted":"01 Jan 15:00","team_h_score":4,"team_a_score":1,"was_home":true,"round":21,"total_points":0,"value":80,"transfers_balance":-7824,"selected":153096,"transfers_in":305,"transfers_out":8129,"loaned_in":0,"loaned_out":0,"minutes":0,"goals_scored":0,"assists":0,"clean_sheets":0,"goals_conceded":0,"own_goals":0,"penalties_saved":0,"penalties_missed":0,"yellow_cards":0,"red_cards":0,"saves":0,"bonus":0,"bps":0,"influence":"0.0","creativity":"0.0","threat":"0.0","ict_index":"0.0","ea_index":0,"open_play_crosses":0,"big_chances_created":0,"clearances_blocks_interceptions":0,"recoveries":0,"key_passes":0,"tackles":0,"winning_goals":0,"attempted_passes":0,"completed_passes":0,"penalties_conceded":0,"big_chances_missed":0,"errors_leading_to_goal":0,"errors_leading_to_goal_attempt":0,"tackled":0,"offside":0,"target_missed":0,"fouls":0,"dribbles":0,"element":13,"fixture":201,"opponent_team":9},{"id":11544,"kickoff_time":"2019-01-12T12:30:00Z","kickoff_time_formatted":"12 Jan 12:30","team_h_score":1,"team_a_score":0,"was_home":false,"round":22,"total_points":0,"value":80,"transfers_balance":-7600,"selected":145989,"transfers_in":475,"transfers_out":8075,"loaned_in":0,"loaned_out":0,"minutes":0,"goals_scored":0,"assists":0,"clean_sheets":0,"goals_conceded":0,"own_goals":0,"penalties_saved":0,"penalties_missed":0,"yellow_cards":0,"red_cards":0,"saves":0,"bonus":0,"bps":0,"influence":"0.0","creativity":"0.0","threat":"0.0","ict_index":"0.0","ea_index":0,"open_play_crosses":0,"big_chances_created":0,"clearances_blocks_interceptions":0,"recoveries":0,"key_passes":0,"tackles":0,"winning_goals":0,"attempted_passes":0,"completed_passes":0,"penalties_conceded":0,"big_chances_missed":0,"errors_leading_to_goal":0,"errors_leading_to_goal_attempt":0,"tackled":0,"offside":0,"target_missed":0,"fouls":0,"dribbles":0,"element":13,"fixture":220,"opponent_team":19},{"id":12118,"kickoff_time":"2019-01-19T17:30:00Z","kickoff_time_formatted":"19 Jan 17:30","team_h_score":2,"team_a_score":0,"was_home":true,"round":23,"total_points":0,"value":80,"transfers_balance":-2098,"selected":144745,"transfers_in":952,"transfers_out":3050,"loaned_in":0,"loaned_out":0,"minutes":0,"goals_scored":0,"assists":0,"clean_sheets":0,"goals_conceded":0,"own_goals":0,"penalties_saved":0,"penalties_missed":0,"yellow_cards":0,"red_cards":0,"saves":0,"bonus":0,"bps":0,"influence":"0.0","creativity":"0.0","threat":"0.0","ict_index":"0.0","ea_index":0,"open_play_crosses":0,"big_chances_created":0,"clearances_blocks_interceptions":0,"recoveries":0,"key_passes":0,"tackles":0,"winning_goals":0,"attempted_passes":0,"completed_passes":0,"penalties_conceded":0,"big_chances_missed":0,"errors_leading_to_goal":0,"errors_leading_to_goal_attempt":0,"tackled":0,"offside":0,"target_missed":0,"fouls":0,"dribbles":0,"element":13,"fixture":221,"opponent_team":6},{"id":12697,"kickoff_time":"2019-01-29T19:45:00Z","kickoff_time_formatted":"29 Jan 19:45","team_h_score":2,"team_a_score":1,"was_home":true,"round":24,"total_points":3,"value":80,"transfers_balance":-1661,"selected":143872,"transfers_in":1139,"transfers_out":2800,"loaned_in":0,"loaned_out":0,"minutes":75,"goals_scored":0,"assists":0,"clean_sheets":1,"goals_conceded":0,"own_goals":0,"penalties_saved":0,"penalties_missed":0,"yellow_cards":0,"red_cards":0,"saves":0,"bonus":0,"bps":15,"influence":"15.4","creativity":"35.6","threat":"4.0","ict_index":"5.5","ea_index":0,"open_play_crosses":0,"big_chances_created":0,"clearances_blocks_interceptions":0,"recoveries":3,"key_passes":2,"tackles":1,"winning_goals":0,"attempted_passes":65,"completed_passes":58,"penalties_conceded":0,"big_chances_missed":0,"errors_leading_to_goal":0,"errors_leading_to_goal_attempt":0,"tackled":0,"offside":0,"target_missed":0,"fouls":0,"dribbles":0,"element":13,"fixture":231,"opponent_team":5},{"id":13280,"kickoff_time":"2019-02-03T16:30:00Z","kickoff_time_formatted":"03 Feb 16:30","team_h_score":3,"team_a_score":1,"was_home":false,"round":25,"total_points":0,"value":80,"transfers_balance":-625,"selected":143592,"transfers_in":762,"transfers_out":1387,"loaned_in":0,"loaned_out":0,"minutes":0,"goals_scored":0,"assists":0,"clean_sheets":0,"goals_conceded":0,"own_goals":0,"penalties_saved":0,"penalties_missed":0,"yellow_cards":0,"red_cards":0,"saves":0,"bonus":0,"bps":0,"influence":"0.0","creativity":"0.0","threat":"0.0","ict_index":"0.0","ea_index":0,"open_play_crosses":0,"big_chances_created":0,"clearances_blocks_interceptions":0,"recoveries":0,"key_passes":0,"tackles":0,"winning_goals":0,"attempted_passes":0,"completed_passes":0,"penalties_conceded":0,"big_chances_missed":0,"errors_leading_to_goal":0,"errors_leading_to_goal_attempt":0,"tackled":0,"offside":0,"target_missed":0,"fouls":0,"dribbles":0,"element":13,"fixture":248,"opponent_team":13},{"id":13934,"kickoff_time":"2019-02-09T15:00:00Z","kickoff_time_formatted":"09 Feb 15:00","team_h_score":1,"team_a_score":2,"was_home":false,"round":26,"total_points":0,"value":80,"transfers_balance":-843,"selected":143490,"transfers_in":1678,"transfers_out":2521,"loaned_in":0,"loaned_out":0,"minutes":0,"goals_scored":0,"assists":0,"clean_sheets":0,"goals_conceded":0,"own_goals":0,"penalties_saved":0,"penalties_missed":0,"yellow_cards":0,"red_cards":0,"saves":0,"bonus":0,"bps":0,"influence":"0.0","creativity":"0.0","threat":"0.0","ict_index":"0.0","ea_index":0,"open_play_crosses":0,"big_chances_created":0,"clearances_blocks_interceptions":0,"recoveries":0,"key_passes":0,"tackles":0,"winning_goals":0,"attempted_passes":0,"completed_passes":0,"penalties_conceded":0,"big_chances_missed":0,"errors_leading_to_goal":0,"errors_leading_to_goal_attempt":0,"tackled":0,"offside":0,"target_missed":0,"fouls":0,"dribbles":0,"element":13,"fixture":254,"opponent_team":10},{"id":14534,"kickoff_time":"2019-02-24T14:05:00Z","kickoff_time_formatted":"24 Feb 14:05","team_h_score":2,"team_a_score":0,"was_home":true,"round":27,"total_points":1,"value":79,"transfers_balance":9,"selected":145542,"transfers_in":3337,"transfers_out":3328,"loaned_in":0,"loaned_out":0,"minutes":27,"goals_scored":0,"assists":0,"clean_sheets":0,"goals_conceded":0,"own_goals":0,"penalties_saved":0,"penalties_missed":0,"yellow_cards":0,"red_cards":0,"saves":0,"bonus":0,"bps":3,"influence":"3.6","creativity":"12.8","threat":"6.0","ict_index":"2.2","ea_index":0,"open_play_crosses":0,"big_chances_created":0,"clearances_blocks_interceptions":0,"recoveries":2,"key_passes":1,"tackles":0,"winning_goals":0,"attempted_passes":20,"completed_passes":18,"penalties_conceded":0,"big_chances_missed":0,"errors_leading_to_goal":0,"errors_leading_to_goal_attempt":0,"tackled":1,"offside":0,"target_missed":0,"fouls":0,"dribbles":0,"element":13,"fixture":261,"opponent_team":16},{"id":15018,"kickoff_time":"2019-02-27T19:45:00Z","kickoff_time_formatted":"27 Feb 19:45","team_h_score":5,"team_a_score":1,"was_home":true,"round":28,"total_points":12,"value":79,"transfers_balance":-654,"selected":143892,"transfers_in":986,"transfers_out":1640,"loaned_in":0,"loaned_out":0,"minutes":90,"goals_scored":1,"assists":1,"clean_sheets":0,"goals_conceded":1,"own_goals":0,"penalties_saved":0,"penalties_missed":0,"yellow_cards":0,"red_cards":0,"saves":0,"bonus":2,"bps":48,"influence":"64.2","creativity":"58.1","threat":"27.0","ict_index":"14.9","ea_index":0,"open_play_crosses":1,"big_chances_created":1,"clearances_blocks_interceptions":1,"recoveries":6,"key_passes":4,"tackles":1,"winning_goals":0,"attempted_passes":65,"completed_passes":63,"penalties_conceded":0,"big_chances_missed":0,"errors_leading_to_goal":0,"errors_leading_to_goal_attempt":0,"tackled":2,"offside":1,"target_missed":1,"fouls":0,"dribbles":1,"element":13,"fixture":271,"opponent_team":2},{"id":15623,"kickoff_time":"2019-03-02T12:30:00Z","kickoff_time_formatted":"02 Mar 12:30","team_h_score":1,"team_a_score":1,"was_home":false,"round":29,"total_points":1,"value":79,"transfers_balance":7025,"selected":151613,"transfers_in":8601,"transfers_out":1576,"loaned_in":0,"loaned_out":0,"minutes":18,"goals_scored":0,"assists":0,"clean_sheets":0,"goals_conceded":1,"own_goals":0,"penalties_saved":0,"penalties_missed":0,"yellow_cards":0,"red_cards":0,"saves":0,"bonus":0,"bps":3,"influence":"1.8","creativity":"4.8","threat":"0.0","ict_index":"0.7","ea_index":0,"open_play_crosses":0,"big_chances_created":0,"clearances_blocks_interceptions":1,"recoveries":1,"key_passes":0,"tackles":0,"winning_goals":0,"attempted_passes":9,"completed_passes":6,"penalties_conceded":0,"big_chances_missed":0,"errors_leading_to_goal":0,"errors_leading_to_goal_attempt":0,"tackled":0,"offside":0,"target_missed":0,"fouls":1,"dribbles":1,"element":13,"fixture":287,"opponent_team":17},{"id":16229,"kickoff_time":"2019-03-10T16:30:00Z","kickoff_time_formatted":"10 Mar 16:30","team_h_score":2,"team_a_score":0,"was_home":true,"round":30,"total_points":3,"value":79,"transfers_balance":-2766,"selected":149382,"transfers_in":1672,"transfers_out":4438,"loaned_in":0,"loaned_out":0,"minutes":76,"goals_scored":0,"assists":0,"clean_sheets":1,"goals_conceded":0,"own_goals":0,"penalties_saved":0,"penalties_missed":0,"yellow_cards":0,"red_cards":0,"saves":0,"bonus":0,"bps":14,"influence":"12.0","creativity":"46.5","threat":"6.0","ict_index":"6.5","ea_index":0,"open_play_crosses":0,"big_chances_created":0,"clearances_blocks_interceptions":2,"recoveries":3,"key_passes":4,"tackles":0,"winning_goals":0,"attempted_passes":34,"completed_passes":31,"penalties_conceded":0,"big_chances_missed":0,"errors_leading_to_goal":0,"errors_leading_to_goal_attempt":0,"tackled":2,"offside":2,"target_missed":0,"fouls":0,"dribbles":0,"element":13,"fixture":291,"opponent_team":14},{"id":17144,"kickoff_time":"2019-04-01T19:00:00Z","kickoff_time_formatted":"01 Apr 20:00","team_h_score":2,"team_a_score":0,"was_home":true,"round":32,"total_points":3,"value":79,"transfers_balance":494,"selected":151072,"transfers_in":3047,"transfers_out":2553,"loaned_in":0,"loaned_out":0,"minutes":83,"goals_scored":0,"assists":0,"clean_sheets":1,"goals_conceded":0,"own_goals":0,"penalties_saved":0,"penalties_missed":0,"yellow_cards":0,"red_cards":0,"saves":0,"bonus":0,"bps":13,"influence":"9.8","creativity":"37.7","threat":"12.0","ict_index":"6.0","ea_index":0,"open_play_crosses":1,"big_chances_created":0,"clearances_blocks_interceptions":0,"recoveries":11,"key_passes":2,"tackles":0,"winning_goals":0,"attempted_passes":71,"completed_passes":63,"penalties_conceded":0,"big_chances_missed":0,"errors_leading_to_goal":0,"errors_leading_to_goal_attempt":0,"tackled":1,"offside":1,"target_missed":0,"fouls":1,"dribbles":0,"element":13,"fixture":311,"opponent_team":15},{"id":18044,"kickoff_time":"2019-04-07T13:05:00Z","kickoff_time_formatted":"07 Apr 14:05","team_h_score":1,"team_a_score":0,"was_home":false,"round":33,"total_points":2,"value":79,"transfers_balance":21698,"selected":176752,"transfers_in":23508,"transfers_out":1810,"loaned_in":0,"loaned_out":0,"minutes":73,"goals_scored":0,"assists":0,"clean_sheets":0,"goals_conceded":1,"own_goals":0,"penalties_saved":0,"penalties_missed":0,"yellow_cards":0,"red_cards":0,"saves":0,"bonus":0,"bps":7,"influence":"3.6","creativity":"5.0","threat":"4.0","ict_index":"1.3","ea_index":0,"open_play_crosses":0,"big_chances_created":0,"clearances_blocks_interceptions":1,"recoveries":2,"key_passes":0,"tackles":0,"winning_goals":0,"attempted_passes":45,"completed_passes":39,"penalties_conceded":0,"big_chances_missed":0,"errors_leading_to_goal":0,"errors_leading_to_goal_attempt":0,"tackled":3,"offside":0,"target_missed":0,"fouls":0,"dribbles":0,"element":13,"fixture":323,"opponent_team":8},{"id":18418,"kickoff_time":"2019-04-15T19:00:00Z","kickoff_time_formatted":"15 Apr 20:00","team_h_score":0,"team_a_score":1,"was_home":false,"round":34,"total_points":1,"value":79,"transfers_balance":-5753,"selected":168078,"transfers_in":4389,"transfers_out":10142,"loaned_in":0,"loaned_out":0,"minutes":45,"goals_scored":0,"assists":0,"clean_sheets":0,"goals_conceded":0,"own_goals":0,"penalties_saved":0,"penalties_missed":0,"yellow_cards":0,"red_cards":0,"saves":0,"bonus":0,"bps":3,"influence":"6.0","creativity":"28.3","threat":"26.0","ict_index":"6.0","ea_index":0,"open_play_crosses":1,"big_chances_created":0,"clearances_blocks_interceptions":0,"recoveries":2,"key_passes":2,"tackles":0,"winning_goals":0,"attempted_passes":22,"completed_passes":20,"penalties_conceded":0,"big_chances_missed":0,"errors_leading_to_goal":0,"errors_leading_to_goal_attempt":0,"tackled":1,"offside":1,"target_missed":0,"fouls":1,"dribbles":0,"element":13,"fixture":340,"opponent_team":18},{"id":19103,"kickoff_time":"2019-04-21T15:00:00Z","kickoff_time_formatted":"21 Apr 16:00","team_h_score":2,"team_a_score":3,"was_home":true,"round":35,"total_points":6,"value":79,"transfers_balance":809,"selected":169726,"transfers_in":6652,"transfers_out":5843,"loaned_in":0,"loaned_out":0,"minutes":90,"goals_scored":1,"assists":0,"clean_sheets":0,"goals_conceded":3,"own_goals":0,"penalties_saved":0,"penalties_missed":0,"yellow_cards":1,"red_cards":0,"saves":0,"bonus":0,"bps":24,"influence":"49.4","creativity":"38.1","threat":"28.0","ict_index":"11.6","ea_index":0,"open_play_crosses":0,"big_chances_created":0,"clearances_blocks_interceptions":0,"recoveries":2,"key_passes":2,"tackles":0,"winning_goals":0,"attempted_passes":81,"completed_passes":76,"penalties_conceded":0,"big_chances_missed":0,"errors_leading_to_goal":0,"errors_leading_to_goal_attempt":0,"tackled":6,"offside":0,"target_missed":0,"fouls":2,"dribbles":3,"element":13,"fixture":341,"opponent_team":7},{"id":19102,"kickoff_time":"2019-04-24T18:45:00Z","kickoff_time_formatted":"24 Apr 19:45","team_h_score":3,"team_a_score":1,"was_home":false,"round":35,"total_points":2,"value":79,"transfers_balance":809,"selected":169726,"transfers_in":6652,"transfers_out":5843,"loaned_in":0,"loaned_out":0,"minutes":90,"goals_scored":0,"assists":0,"clean_sheets":0,"goals_conceded":3,"own_goals":0,"penalties_saved":0,"penalties_missed":0,"yellow_cards":0,"red_cards":0,"saves":0,"bonus":0,"bps":8,"influence":"11.6","creativity":"36.6","threat":"4.0","ict_index":"5.2","ea_index":0,"open_play_crosses":1,"big_chances_created":0,"clearances_blocks_interceptions":0,"recoveries":4,"key_passes":2,"tackles":0,"winning_goals":0,"attempted_passes":77,"completed_passes":67,"penalties_conceded":0,"big_chances_missed":0,"errors_leading_to_goal":0,"errors_leading_to_goal_attempt":0,"tackled":7,"offside":0,"target_missed":0,"fouls":0,"dribbles":1,"element":13,"fixture":310,"opponent_team":20},{"id":19949,"kickoff_time":"2019-04-28T11:00:00Z","kickoff_time_formatted":"28 Apr 12:00","team_h_score":3,"team_a_score":0,"was_home":false,"round":36,"total_points":0,"value":79,"transfers_balance":-3584,"selected":166225,"transfers_in":2300,"transfers_out":5884,"loaned_in":0,"loaned_out":0,"minutes":0,"goals_scored":0,"assists":0,"clean_sheets":0,"goals_conceded":0,"own_goals":0,"penalties_saved":0,"penalties_missed":0,"yellow_cards":0,"red_cards":0,"saves":0,"bonus":0,"bps":0,"influence":"0.0","creativity":"0.0","threat":"0.0","ict_index":"0.0","ea_index":0,"open_play_crosses":0,"big_chances_created":0,"clearances_blocks_interceptions":0,"recoveries":0,"key_passes":0,"tackles":0,"winning_goals":0,"attempted_passes":0,"completed_passes":0,"penalties_conceded":0,"big_chances_missed":0,"errors_leading_to_goal":0,"errors_leading_to_goal_attempt":0,"tackled":0,"offside":0,"target_missed":0,"fouls":0,"dribbles":0,"element":13,"fixture":355,"opponent_team":11},{"id":20564,"kickoff_time":"2019-05-05T15:30:00Z","kickoff_time_formatted":"05 May 16:30","team_h_score":1,"team_a_score":1,"was_home":true,"round":37,"total_points":2,"value":79,"transfers_balance":-6482,"selected":159888,"transfers_in":1349,"transfers_out":7831,"loaned_in":0,"loaned_out":0,"minutes":90,"goals_scored":0,"assists":0,"clean_sheets":0,"goals_conceded":1,"own_goals":0,"penalties_saved":0,"penalties_missed":0,"yellow_cards":0,"red_cards":0,"saves":0,"bonus":0,"bps":16,"influence":"15.8","creativity":"47.7","threat":"4.0","ict_index":"6.8","ea_index":0,"open_play_crosses":1,"big_chances_created":0,"clearances_blocks_interceptions":1,"recoveries":3,"key_passes":3,"tackles":0,"winning_goals":0,"attempted_passes":60,"completed_passes":55,"penalties_conceded":0,"big_chances_missed":0,"errors_leading_to_goal":0,"errors_leading_to_goal_attempt":0,"tackled":3,"offside":1,"target_missed":0,"fouls":0,"dribbles":3,"element":13,"fixture":361,"opponent_team":3},{"id":21180,"kickoff_time":"2019-05-12T14:00:00Z","kickoff_time_formatted":"12 May 15:00","team_h_score":1,"team_a_score":3,"was_home":false,"round":38,"total_points":0,"value":79,"transfers_balance":1434,"selected":162012,"transfers_in":4531,"transfers_out":3097,"loaned_in":0,"loaned_out":0,"minutes":0,"goals_scored":0,"assists":0,"clean_sheets":0,"goals_conceded":0,"own_goals":0,"penalties_saved":0,"penalties_missed":0,"yellow_cards":0,"red_cards":0,"saves":0,"bonus":0,"bps":0,"influence":"0.0","creativity":"0.0","threat":"0.0","ict_index":"0.0","ea_index":0,"open_play_crosses":0,"big_chances_created":0,"clearances_blocks_interceptions":0,"recoveries":0,"key_passes":0,"tackles":0,"winning_goals":0,"attempted_passes":0,"completed_passes":0,"penalties_conceded":0,"big_chances_missed":0,"errors_leading_to_goal":0,"errors_leading_to_goal_attempt":0,"tackled":0,"offside":0,"target_missed":0,"fouls":0,"dribbles":0,"element":13,"fixture":372,"opponent_team":4}]}