{"history_past":[{"id":8006,"season_name":"2017/18","element_code":246878,"start_cost":50,"end_cost":47,"total_points":10,"minutes":217,"goals_scored":0,"assists":1,"clean_sheets":1,"goals_conceded":5,"own_goals":0,"penalties_saved":0,"penalties_missed":0,"yellow_cards":1,"red_cards":0,"saves":0,"bonus":0,"bps":30,"influence":"30.8","creativity":"40.6","threat":"53.0","ict_index":"12.4","ea_index":0,"season":12}],"fixtures_summary":[],"explain":[{"explain":{"minutes":{"points":0,"name":"Minutes played","value":0}},"fixture":{"id":378,"kickoff_time_formatted":"12 May 15:00","started":true,"event_day":1,"deadline_time":"2019-05-12T13:00:00Z","deadline_time_formatted":"12 May 14:00","stats":[{"goals_scored":{"a":[{"value":1,"element":206}],"h":[{"value":1,"element":343}]}},{"assists":{"a":[],"h":[{"value":1,"element":258}]}},{"own_goals":{"a":[],"h":[]}},{"penalties_saved":{"a":[],"h":[]}},{"penalties_missed":{"a":[],"h":[]}},{"yellow_cards":{"a":[{"value":1,"element":201}],"h":[]}},{"red_cards":{"a":[],"h":[]}},{"saves":{"a":[{"value":2,"element":598}],"h":[{"value":2,"element":452}]}},{"bonus":{"a":[{"value":2,"element":206},{"value":1,"element":198}],"h":[{"value":3,"element":343}]}},{"bps":{"a":[{"value":30,"element":206},{"value":17,"element":198},{"value":14,"element":199},{"value":13,"element":598},{"value":12,"element":192},{"value":10,"element":194},{"value":9,"element":522},{"value":7,"element":514},{"value":6,"element":208},{"value":4,"element":585},{"value":3,"element":606},{"value":2,"element":201},{"value":2,"element":211}],"h":[{"value":38,"element":343},{"value":15,"element":340},{"value":13,"element":339},{"value":12,"element":258},{"value":12,"element":335},{"value":12,"element":338},{"value":9,"element":333},{"value":8,"element":330},{"value":8,"element":452},{"value":6,"element":479},{"value":3,"element":342},{"value":2,"element":348},{"value":2,"element":556},{"value":-3,"element":347}]}}],"code":987969,"kickoff_time":"2019-05-12T14:00:00Z","team_h_score":1,"team_a_score":1,"finished":true,"minutes":90,"provisional_start_time":false,"finished_provisional":true,"event":38,"team_a":10,"team_h":16}}],"history_summary":[{"id":20141,"kickoff_time":"2019-04-26T19:00:00Z","kickoff_time_formatted":"26 Apr 20:00","team_h_score":5,"team_a_score":0,"was_home":false,"round":36,"total_points":0,"value":43,"transfers_balance":-14,"selected":2895,"transfers_in":18,"transfers_out":32,"loaned_in":0,"loaned_out":0,"minutes":0,"goals_scored":0,"assists":0,"clean_sheets":0,"goals_conceded":0,"own_goals":0,"penalties_saved":0,"penalties_missed":0,"yellow_cards":0,"red_cards":0,"saves":0,"bonus":0,"bps":0,"influence":"0.0","creativity":"0.0","threat":"0.0","ict_index":"0.0","ea_index":0,"open_play_crosses":0,"big_chances_created":0,"clearances_blocks_interceptions":0,"recoveries":0,"key_passes":0,"tackles":0,"winning_goals":0,"attempted_passes":0,"completed_passes":0,"penalties_conceded":0,"big_chances_missed":0,"errors_leading_to_goal":0,"errors_leading_to_goal_attempt":0,"tackled":0,"offside":0,"target_missed":0,"fouls":0,"dribbles":0,"element":205,"fixture":356,"opponent_team":12},{"id":20756,"kickoff_time":"2019-05-05T13:00:00Z","kickoff_time_formatted":"05 May 14:00","team_h_score":1,"team_a_score":1,"was_home":true,"round":37,"total_points":0,"value":43,"transfers_balance":1,"selected":2893,"transfers_in":45,"transfers_out":44,"loaned_in":0,"loaned_out":0,"minutes":0,"goals_scored":0,"assists":0,"clean_sheets":0,"goals_conceded":0,"own_goals":0,"penalties_saved":0,"penalties_missed":0,"yellow_cards":0,"red_cards":0,"saves":0,"bonus":0,"bps":0,"influence":"0.0","creativity":"0.0","threat":"0.0","ict_index":"0.0","ea_index":0,"open_play_crosses":0,"big_chances_created":0,"clearances_blocks_interceptions":0,"recoveries":0,"key_passes":0,"tackles":0,"winning_goals":0,"attempted_passes":0,"completed_passes":0,"penalties_conceded":0,"big_chances_missed":0,"errors_leading_to_goal":0,"errors_leading_to_goal_attempt":0,"tackled":0,"offside":0,"target_missed":0,"fouls":0,"dribbles":0,"element":205,"fixture":366,"opponent_team":14},{"id":21372,"kickoff_time":"2019-05-12T14:00:00Z","kickoff_time_formatted":"12 May 15:00","team_h_score":1,"team_a_score":1,"was_home":false,"round":38,"total_points":0,"value":43,"transfers_balance":13,"selected":2914,"transfers_in":55,"transfers_out":42,"loaned_in":0,"loaned_out":0,"minutes":0,"goals_scored":0,"assists":0,"clean_sheets":0,"goals_conceded":0,"own_goals":0,"penalties_saved":0,"penalties_missed":0,"yellow_cards":0,"red_cards":0,"saves":0,"bonus":0,"bps":0,"influence":"0.0","creativity":"0.0","threat":"0.0","ict_index":"0.0","ea_index":0,"open_play_crosses":0,"big_chances_created":0,"clearances_blocks_interceptions":0,"recoveries":0,"key_passes":0,"tackles":0,"winning_goals":0,"attempted_passes":0,"completed_passes":0,"penalties_conceded":0,"big_chances_missed":0,"errors_leading_to_goal":0,"errors_leading_to_goal_attempt":0,"tackled":0,"offside":0,"target_missed":0,"fouls":0,"dribbles":0,"element":205,"fixture":378,"opponent_team":16}],"fixtures":[],"history":[{"id":205,"kickoff_time":"2018-08-11T14:00:00Z","kickoff_time_formatted":"11 Aug 15:00","team_h_score":0,"team_a_score":3,"was_home":true,"round":1,"total_points":0,"value":45,"transfers_balance":0,"selected":3471,"transfers_in":0,"transfers_out":0,"loaned_in":0,"loaned_out":0,"minutes":0,"goals_scored":0,"assists":0,"clean_sheets":0,"goals_conceded":0,"own_goals":0,"penalties_saved":0,"penalties_missed":0,"yellow_cards":0,"red_cards":0,"saves":0,"bonus":0,"bps":0,"influence":"0.0","creativity":"0.0","threat":"0.0","ict_index":"0.0","ea_index":0,"open_play_crosses":0,"big_chances_created":0,"clearances_blocks_interceptions":0,"recoveries":0,"key_passes":0,"tackles":0,"winning_goals":0,"attempted_passes":0,"completed_passes":0,"penalties_conceded":0,"big_chances_missed":0,"errors_leading_to_goal":0,"errors_leading_to_goal_attempt":0,"tackled":0,"offside":0,"target_missed":0,"fouls":0,"dribbles":0,"element":205,"fixture":4,"opponent_team":6},{"id":730,"kickoff_time":"2018-08-19T12:30:00Z","kickoff_time_formatted":"19 Aug 13:30","team_h_score":6,"team_a_score":1,"was_home":false,"round":2,"total_points":1,"value":45,"transfers_balance":-386,"selected":3461,"transfers_in":93,"transfers_out":479,"loaned_in":0,"loaned_out":0,"minutes":45,"goals_scored":0,"assists":0,"clean_sheets":0,"goals_conceded":3,"own_goals":0,"penalties_saved":0,"penalties_missed":0,"yellow_cards":0,"red_cards":0,"saves":0,"bonus":0,"bps":3,"influence":"4.2","creativity":"0.5","threat":"2.0","ict_index":"0.7","ea_index":0,"open_play_crosses":0,"big_chances_created":0,"clearances_blocks_interceptions":1,"recoveries":2,"key_passes":0,"tackles":0,"winning_goals":0,"attempted_passes":8,"completed_passes":7,"penalties_conceded":0,"big_chances_missed":0,"errors_leading_to_goal":0,"errors_leading_to_goal_attempt":0,"tackled":0,"offside":0,"target_missed":0,"fouls":0,"dribbles":0,"element":205,"fixture":18,"opponent_team":13},{"id":1257,"kickoff_time":"2018-08-25T14:00:00Z","kickoff_time_formatted":"25 Aug 15:00","team_h_score":0,"team_a_score":0,"was_home":true,"round":3,"total_points":0,"value":45,"transfers_balance":-170,"selected":3483,"transfers_in":275,"transfers_out":445,"loaned_in":0,"loaned_out":0,"minutes":0,"goals_scored":0,"assists":0,"clean_sheets":0,"goals_conceded":0,"own_goals":0,"penalties_saved":0,"penalties_missed":0,"yellow_cards":0,"red_cards":0,"saves":0,"bonus":0,"bps":0,"influence":"0.0","creativity":"0.0","threat":"0.0","ict_index":"0.0","ea_index":0,"open_play_crosses":0,"big_chances_created":0,"clearances_blocks_interceptions":0,"recoveries":0,"key_passes":0,"tackles":0,"winning_goals":0,"attempted_passes":0,"completed_passes":0,"penalties_conceded":0,"big_chances_missed":0,"errors_leading_to_goal":0,"errors_leading_to_goal_attempt":0,"tackled":0,"offside":0,"target_missed":0,"fouls":0,"dribbles":0,"element":205,"fixture":24,"opponent_team":5},{"id":1788,"kickoff_time":"2018-09-01T14:00:00Z","kickoff_time_formatted":"01 Sep 15:00","team_h_score":1,"team_a_score":1,"was_home":false,"round":4,"total_points":0,"value":45,"transfers_balance":-260,"selected":3287,"transfers_in":105,"transfers_out":365,"loaned_in":0,"loaned_out":0,"minutes":0,"goals_scored":0,"assists":0,"clean_sheets":0,"goals_conceded":0,"own_goals":0,"penalties_saved":0,"penalties_missed":0,"yellow_cards":0,"red_cards":0,"saves":0,"bonus":0,"bps":0,"influence":"0.0","creativity":"0.0","threat":"0.0","ict_index":"0.0","ea_index":0,"open_play_crosses":0,"big_chances_created":0,"clearances_blocks_interceptions":0,"recoveries":0,"key_passes":0,"tackles":0,"winning_goals":0,"attempted_passes":0,"completed_passes":0,"penalties_conceded":0,"big_chances_missed":0,"errors_leading_to_goal":0,"errors_leading_to_goal_attempt":0,"tackled":0,"offside":0,"target_missed":0,"fouls":0,"dribbles":0,"element":205,"fixture":36,"opponent_team":8},{"id":2325,"kickoff_time":"2018-09-15T14:00:00Z","kickoff_time_formatted":"15 Sep 15:00","team_h_score":0,"team_a_score":1,"was_home":true,"round":5,"total_points":0,"value":44,"transfers_balance":218,"selected":3822,"transfers_in":861,"transfers_out":643,"loaned_in":0,"loaned_out":0,"minutes":0,"goals_scored":0,"assists":0,"clean_sheets":0,"goals_conceded":0,"own_goals":0,"penalties_saved":0,"penalties_missed":0,"yellow_cards":0,"red_cards":0,"saves":0,"bonus":0,"bps":0,"influence":"0.0","creativity":"0.0","threat":"0.0","ict_index":"0.0","ea_index":0,"open_play_crosses":0,"big_chances_created":0,"clearances_blocks_interceptions":0,"recoveries":0,"key_passes":0,"tackles":0,"winning_goals":0,"attempted_passes":0,"completed_passes":0,"penalties_conceded":0,"big_chances_missed":0,"errors_leading_to_goal":0,"errors_leading_to_goal_attempt":0,"tackled":0,"offside":0,"target_missed":0,"fouls":0,"dribbles":0,"element":205,"fixture":44,"opponent_team":7},{"id":2862,"kickoff_time":"2018-09-22T14:00:00Z","kickoff_time_formatted":"22 Sep 15:00","team_h_score":3,"team_a_score":1,"was_home":false,"round":6,"total_points":0,"value":44,"transfers_balance":-193,"selected":3546,"transfers_in":133,"transfers_out":326,"loaned_in":0,"loaned_out":0,"minutes":0,"goals_scored":0,"assists":0,"clean_sheets":0,"goals_conceded":0,"own_goals":0,"penalties_saved":0,"penalties_missed":0,"yellow_cards":0,"red_cards":0,"saves":0,"bonus":0,"bps":0,"influence":"0.0","creativity":"0.0","threat":"0.0","ict_index":"0.0","ea_index":0,"open_play_crosses":0,"big_chances_created":0,"clearances_blocks_interceptions":0,"recoveries":0,"key_passes":0,"tackles":0,"winning_goals":0,"attempted_passes":0,"completed_passes":0,"penalties_conceded":0,"big_chances_missed":0,"errors_leading_to_goal":0,"errors_leading_to_goal_attempt":0,"tackled":0,"offside":0,"target_missed":0,"fouls":0,"dribbles":0,"element":205,"fixture":57,"opponent_team":11},{"id":3400,"kickoff_time":"2018-09-29T14:00:00Z","kickoff_time_formatted":"29 Sep 15:00","team_h_score":0,"team_a_score":2,"was_home":true,"round":7,"total_points":0,"value":44,"transfers_balance":-174,"selected":3419,"transfers_in":70,"transfers_out":244,"loaned_in":0,"loaned_out":0,"minutes":0,"goals_scored":0,"assists":0,"clean_sheets":0,"goals_conceded":0,"own_goals":0,"penalties_saved":0,"penalties_missed":0,"yellow_cards":0,"red_cards":0,"saves":0,"bonus":0,"bps":0,"influence":"0.0","creativity":"0.0","threat":"0.0","ict_index":"0.0","ea_index":0,"open_play_crosses":0,"big_chances_created":0,"clearances_blocks_interceptions":0,"recoveries":0,"key_passes":0,"tackles":0,"winning_goals":0,"attempted_passes":0,"completed_passes":0,"penalties_conceded":0,"big_chances_missed":0,"errors_leading_to_goal":0,"errors_leading_to_goal_attempt":0,"tackled":0,"offside":0,"target_missed":0,"fouls":0,"dribbles":0,"element":205,"fixture":66,"opponent_team":17},{"id":3939,"kickoff_time":"2018-10-06T14:00:00Z","kickoff_time_formatted":"06 Oct 15:00","team_h_score":1,"team_a_score":1,"was_home":false,"round":8,"total_points":0,"value":44,"transfers_balance":-92,"selected":3362,"transfers_in":86,"transfers_out":178,"loaned_in":0,"loaned_out":0,"minutes":0,"goals_scored":0,"assists":0,"clean_sheets":0,"goals_conceded":0,"own_goals":0,"penalties_saved":0,"penalties_missed":0,"yellow_cards":0,"red_cards":0,"saves":0,"bonus":0,"bps":0,"influence":"0.0","creativity":"0.0","threat":"0.0","ict_index":"0.0","ea_index":0,"open_play_crosses":0,"big_chances_created":0,"clearances_blocks_interceptions":0,"recoveries":0,"key_passes":0,"tackles":0,"winning_goals":0,"attempted_passes":0,"completed_passes":0,"penalties_conceded":0,"big_chances_missed":0,"errors_leading_to_goal":0,"errors_leading_to_goal_attempt":0,"tackled":0,"offside":0,"target_missed":0,"fouls":0,"dribbles":0,"element":205,"fixture":72,"opponent_team":4},{"id":4481,"kickoff_time":"2018-10-20T16:30:00Z","kickoff_time_formatted":"20 Oct 17:30","team_h_score":0,"team_a_score":1,"was_home":true,"round":9,"total_points":0,"value":44,"transfers_balance":-289,"selected":3062,"transfers_in":25,"transfers_out":314,"loaned_in":0,"loaned_out":0,"minutes":0,"goals_scored":0,"assists":0,"clean_sheets":0,"goals_conceded":0,"own_goals":0,"penalties_saved":0,"penalties_missed":0,"yellow_cards":0,"red_cards":0,"saves":0,"bonus":0,"bps":0,"influence":"0.0","creativity":"0.0","threat":"0.0","ict_index":"0.0","ea_index":0,"open_play_crosses":0,"big_chances_created":0,"clearances_blocks_interceptions":0,"recoveries":0,"key_passes":0,"tackles":0,"winning_goals":0,"attempted_passes":0,"completed_passes":0,"penalties_conceded":0,"big_chances_missed":0,"errors_leading_to_goal":0,"errors_leading_to_goal_attempt":0,"tackled":0,"offside":0,"target_missed":0,"fouls":0,"dribbles":0,"element":205,"fixture":86,"opponent_team":12},{"id":5027,"kickoff_time":"2018-10-27T14:00:00Z","kickoff_time_formatted":"27 Oct 15:00","team_h_score":3,"team_a_score":0,"was_home":false,"round":10,"total_points":0,"value":43,"transfers_balance":198,"selected":3486,"transfers_in":436,"transfers_out":238,"loaned_in":0,"loaned_out":0,"minutes":0,"goals_scored":0,"assists":0,"clean_sheets":0,"goals_conceded":0,"own_goals":0,"penalties_saved":0,"penalties_missed":0,"yellow_cards":0,"red_cards":0,"saves":0,"bonus":0,"bps":0,"influence":"0.0","creativity":"0.0","threat":"0.0","ict_index":"0.0","ea_index":0,"open_play_crosses":0,"big_chances_created":0,"clearances_blocks_interceptions":0,"recoveries":0,"key_passes":0,"tackles":0,"winning_goals":0,"attempted_passes":0,"completed_passes":0,"penalties_conceded":0,"big_chances_missed":0,"errors_leading_to_goal":0,"errors_leading_to_goal_attempt":0,"tackled":0,"offside":0,"target_missed":0,"fouls":0,"dribbles":0,"element":205,"fixture":100,"opponent_team":18},{"id":5575,"kickoff_time":"2018-11-05T20:00:00Z","kickoff_time_formatted":"05 Nov 20:00","team_h_score":1,"team_a_score":0,"was_home":true,"round":11,"total_points":0,"value":43,"transfers_balance":376,"selected":4086,"transfers_in":743,"transfers_out":367,"loaned_in":0,"loaned_out":0,"minutes":0,"goals_scored":0,"assists":0,"clean_sheets":0,"goals_conceded":0,"own_goals":0,"penalties_saved":0,"penalties_missed":0,"yellow_cards":0,"red_cards":0,"saves":0,"bonus":0,"bps":0,"influence":"0.0","creativity":"0.0","threat":"0.0","ict_index":"0.0","ea_index":0,"open_play_crosses":0,"big_chances_created":0,"clearances_blocks_interceptions":0,"recoveries":0,"key_passes":0,"tackles":0,"winning_goals":0,"attempted_passes":0,"completed_passes":0,"penalties_conceded":0,"big_chances_missed":0,"errors_leading_to_goal":0,"errors_leading_to_goal_attempt":0,"tackled":0,"offside":0,"target_missed":0,"fouls":0,"dribbles":0,"element":205,"fixture":106,"opponent_team":9},{"id":6125,"kickoff_time":"2018-11-10T15:00:00Z","kickoff_time_formatted":"10 Nov 15:00","team_h_score":1,"team_a_score":1,"was_home":true,"round":12,"total_points":0,"value":43,"transfers_balance":97,"selected":4165,"transfers_in":370,"transfers_out":273,"loaned_in":0,"loaned_out":0,"minutes":0,"goals_scored":0,"assists":0,"clean_sheets":0,"goals_conceded":0,"own_goals":0,"penalties_saved":0,"penalties_missed":0,"yellow_cards":0,"red_cards":0,"saves":0,"bonus":0,"bps":0,"influence":"0.0","creativity":"0.0","threat":"0.0","ict_index":"0.0","ea_index":0,"open_play_crosses":0,"big_chances_created":0,"clearances_blocks_interceptions":0,"recoveries":0,"key_passes":0,"tackles":0,"winning_goals":0,"attempted_passes":0,"completed_passes":0,"penalties_conceded":0,"big_chances_missed":0,"errors_leading_to_goal":0,"errors_leading_to_goal_attempt":0,"tackled":0,"offside":0,"target_missed":0,"fouls":0,"dribbles":0,"element":205,"fixture":115,"opponent_team":19},{"id":6677,"kickoff_time":"2018-11-25T16:00:00Z","kickoff_time_formatted":"25 Nov 16:00","team_h_score":0,"team_a_score":2,"was_home":false,"round":13,"total_points":0,"value":43,"transfers_balance":-47,"selected":4109,"transfers_in":211,"transfers_out":258,"loaned_in":0,"loaned_out":0,"minutes":0,"goals_scored":0,"assists":0,"clean_sheets":0,"goals_conceded":0,"own_goals":0,"penalties_saved":0,"penalties_missed":0,"yellow_cards":0,"red_cards":0,"saves":0,"bonus":0,"bps":0,"influence":"0.0","creativity":"0.0","threat":"0.0","ict_index":"0.0","ea_index":0,"open_play_crosses":0,"big_chances_created":0,"clearances_blocks_interceptions":0,"recoveries":0,"key_passes":0,"tackles":0,"winning_goals":0,"attempted_passes":0,"completed_passes":0,"penalties_conceded":0,"big_chances_missed":0,"errors_leading_to_goal":0,"errors_leading_to_goal_attempt":0,"tackled":0,"offside":0,"target_missed":0,"fouls":0,"dribbles":0,"element":205,"fixture":130,"opponent_team":20},{"id":7230,"kickoff_time":"2018-12-01T15:00:00Z","kickoff_time_formatted":"01 Dec 15:00","team_h_score":1,"team_a_score":2,"was_home":true,"round":14,"total_points":0,"value":43,"transfers_balance":4,"selected":4126,"transfers_in":134,"transfers_out":130,"loaned_in":0,"loaned_out":0,"minutes":0,"goals_scored":0,"assists":0,"clean_sheets":0,"goals_conceded":0,"own_goals":0,"penalties_saved":0,"penalties_missed":0,"yellow_cards":0,"red_cards":0,"saves":0,"bonus":0,"bps":0,"influence":"0.0","creativity":"0.0","threat":"0.0","ict_index":"0.0","ea_index":0,"open_play_crosses":0,"big_chances_created":0,"clearances_blocks_interceptions":0,"recoveries":0,"key_passes":0,"tackles":0,"winning_goals":0,"attempted_passes":0,"completed_passes":0,"penalties_conceded":0,"big_chances_missed":0,"errors_leading_to_goal":0,"errors_leading_to_goal_attempt":0,"tackled":0,"offside":0,"target_missed":0,"fouls":0,"dribbles":0,"element":205,"fixture":135,"opponent_team":3},{"id":7786,"kickoff_time":"2018-12-04T19:45:00Z","kickoff_time_formatted":"04 Dec 19:45","team_h_score":2,"team_a_score":1,"was_home":false,"round":15,"total_points":1,"value":43,"transfers_balance":-49,"selected":4092,"transfers_in":107,"transfers_out":156,"loaned_in":0,"loaned_out":0,"minutes":3,"goals_scored":0,"assists":0,"clean_sheets":0,"goals_conceded":0,"own_goals":0,"penalties_saved":0,"penalties_missed":0,"yellow_cards":0,"red_cards":0,"saves":0,"bonus":0,"bps":3,"influence":"0.0","creativity":"0.0","threat":"0.0","ict_index":"0.0","ea_index":0,"open_play_crosses":0,"big_chances_created":0,"clearances_blocks_interceptions":0,"recoveries":0,"key_passes":0,"tackles":0,"winning_goals":0,"attempted_passes":0,"completed_passes":0,"penalties_conceded":0,"big_chances_missed":0,"errors_leading_to_goal":0,"errors_leading_to_goal_attempt":0,"tackled":0,"offside":0,"target_missed":0,"fouls":0,"dribbles":0,"element":205,"fixture":141,"opponent_team":2},{"id":8344,"kickoff_time":"2018-12-08T15:00:00Z","kickoff_time_formatted":"08 Dec 15:00","team_h_score":1,"team_a_score":0,"was_home":false,"round":16,"total_points":0,"value":43,"transfers_balance":-218,"selected":3841,"transfers_in":35,"transfers_out":253,"loaned_in":0,"loaned_out":0,"minutes":0,"goals_scored":0,"assists":0,"clean_sheets":0,"goals_conceded":0,"own_goals":0,"penalties_saved":0,"penalties_missed":0,"yellow_cards":0,"red_cards":0,"saves":0,"bonus":0,"bps":0,"influence":"0.0","creativity":"0.0","threat":"0.0","ict_index":"0.0","ea_index":0,"open_play_crosses":0,"big_chances_created":0,"clearances_blocks_interceptions":0,"recoveries":0,"key_passes":0,"tackles":0,"winning_goals":0,"attempted_passes":0,"completed_passes":0,"penalties_conceded":0,"big_chances_missed":0,"errors_leading_to_goal":0,"errors_leading_to_goal_attempt":0,"tackled":0,"offside":0,"target_missed":0,"fouls":0,"dribbles":0,"element":205,"fixture":151,"opponent_team":1},{"id":8903,"kickoff_time":"2018-12-15T15:00:00Z","kickoff_time_formatted":"15 Dec 15:00","team_h_score":0,"team_a_score":1,"was_home":true,"round":17,"total_points":0,"value":43,"transfers_balance":-236,"selected":3615,"transfers_in":26,"transfers_out":262,"loaned_in":0,"loaned_out":0,"minutes":0,"goals_scored":0,"assists":0,"clean_sheets":0,"goals_conceded":0,"own_goals":0,"penalties_saved":0,"penalties_missed":0,"yellow_cards":0,"red_cards":0,"saves":0,"bonus":0,"bps":0,"influence":"0.0","creativity":"0.0","threat":"0.0","ict_index":"0.0","ea_index":0,"open_play_crosses":0,"big_chances_created":0,"clearances_blocks_interceptions":0,"recoveries":0,"key_passes":0,"tackles":0,"winning_goals":0,"attempted_passes":0,"completed_passes":0,"penalties_conceded":0,"big_chances_missed":0,"errors_leading_to_goal":0,"errors_leading_to_goal_attempt":0,"tackled":0,"offside":0,"target_missed":0,"fouls":0,"dribbles":0,"element":205,"fixture":164,"opponent_team":15},{"id":9465,"kickoff_time":"2018-12-22T15:00:00Z","kickoff_time_formatted":"22 Dec 15:00","team_h_score":1,"team_a_score":3,"was_home":true,"round":18,"total_points":0,"value":43,"transfers_balance":-141,"selected":3490,"transfers_in":26,"transfers_out":167,"loaned_in":0,"loaned_out":0,"minutes":0,"goals_scored":0,"assists":0,"clean_sheets":0,"goals_conceded":0,"own_goals":0,"penalties_saved":0,"penalties_missed":0,"yellow_cards":0,"red_cards":0,"saves":0,"bonus":0,"bps":0,"influence":"0.0","creativity":"0.0","threat":"0.0","ict_index":"0.0","ea_index":0,"open_play_crosses":0,"big_chances_created":0,"clearances_blocks_interceptions":0,"recoveries":0,"key_passes":0,"tackles":0,"winning_goals":0,"attempted_passes":0,"completed_passes":0,"penalties_conceded":0,"big_chances_missed":0,"errors_leading_to_goal":0,"errors_leading_to_goal_attempt":0,"tackled":0,"offside":0,"target_missed":0,"fouls":0,"dribbles":0,"element":205,"fixture":176,"opponent_team":16},{"id":10030,"kickoff_time":"2018-12-26T15:00:00Z","kickoff_time_formatted":"26 Dec 15:00","team_h_score":3,"team_a_score":1,"was_home":false,"round":19,"total_points":0,"value":43,"transfers_balance":-128,"selected":3366,"transfers_in":9,"transfers_out":137,"loaned_in":0,"loaned_out":0,"minutes":0,"goals_scored":0,"assists":0,"clean_sheets":0,"goals_conceded":0,"own_goals":0,"penalties_saved":0,"penalties_missed":0,"yellow_cards":0,"red_cards":0,"saves":0,"bonus":0,"bps":0,"influence":"0.0","creativity":"0.0","threat":"0.0","ict_index":"0.0","ea_index":0,"open_play_crosses":0,"big_chances_created":0,"clearances_blocks_interceptions":0,"recoveries":0,"key_passes":0,"tackles":0,"winning_goals":0,"attempted_passes":0,"completed_passes":0,"penalties_conceded":0,"big_chances_missed":0,"errors_leading_to_goal":0,"errors_leading_to_goal_attempt":0,"tackled":0,"offside":0,"target_missed":0,"fouls":0,"dribbles":0,"element":205,"fixture":187,"opponent_team":14},{"id":10598,"kickoff_time":"2018-12-29T15:00:00Z","kickoff_time_formatted":"29 Dec 15:00","team_h_score":1,"team_a_score":0,"was_home":false,"round":20,"total_points":0,"value":43,"transfers_balance":-99,"selected":3265,"transfers_in":24,"transfers_out":123,"loaned_in":0,"loaned_out":0,"minutes":0,"goals_scored":0,"assists":0,"clean_sheets":0,"goals_conceded":0,"own_goals":0,"penalties_saved":0,"penalties_missed":0,"yellow_cards":0,"red_cards":0,"saves":0,"bonus":0,"bps":0,"influence":"0.0","creativity":"0.0","threat":"0.0","ict_index":"0.0","ea_index":0,"open_play_crosses":0,"big_chances_created":0,"clearances_blocks_interceptions":0,"recoveries":0,"key_passes":0,"tackles":0,"winning_goals":0,"attempted_passes":0,"completed_passes":0,"penalties_conceded":0,"big_chances_missed":0,"errors_leading_to_goal":0,"errors_leading_to_goal_attempt":0,"tackled":0,"offside":0,"target_missed":0,"fouls":0,"dribbles":0,"element":205,"fixture":194,"opponent_team":9},{"id":11166,"kickoff_time":"2019-01-02T19:45:00Z","kickoff_time_formatted":"02 Jan 19:45","team_h_score":1,"team_a_score":2,"was_home":true,"round":21,"total_points":0,"value":43,"transfers_balance":-86,"selected":3188,"transfers_in":30,"transfers_out":116,"loaned_in":0,"loaned_out":0,"minutes":0,"goals_scored":0,"assists":0,"clean_sheets":0,"goals_conceded":0,"own_goals":0,"penalties_saved":0,"penalties_missed":0,"yellow_cards":0,"red_cards":0,"saves":0,"bonus":0,"bps":0,"influence":"0.0","creativity":"0.0","threat":"0.0","ict_index":"0.0","ea_index":0,"open_play_crosses":0,"big_chances_created":0,"clearances_blocks_interceptions":0,"recoveries":0,"key_passes":0,"tackles":0,"winning_goals":0,"attempted_passes":0,"completed_passes":0,"penalties_conceded":0,"big_chances_missed":0,"errors_leading_to_goal":0,"errors_leading_to_goal_attempt":0,"tackled":0,"offside":0,"target_missed":0,"fouls":0,"dribbles":0,"element":205,"fixture":206,"opponent_team":4},{"id":11736,"kickoff_time":"2019-01-12T15:00:00Z","kickoff_time_formatted":"12 Jan 15:00","team_h_score":0,"team_a_score":0,"was_home":false,"round":22,"total_points":0,"value":43,"transfers_balance":-111,"selected":3086,"transfers_in":60,"transfers_out":171,"loaned_in":0,"loaned_out":0,"minutes":0,"goals_scored":0,"assists":0,"clean_sheets":0,"goals_conceded":0,"own_goals":0,"penalties_saved":0,"penalties_missed":0,"yellow_cards":0,"red_cards":0,"saves":0,"bonus":0,"bps":0,"influence":"0.0","creativity":"0.0","threat":"0.0","ict_index":"0.0","ea_index":0,"open_play_crosses":0,"big_chances_created":0,"clearances_blocks_interceptions":0,"recoveries":0,"key_passes":0,"tackles":0,"winning_goals":0,"attempted_passes":0,"completed_passes":0,"penalties_conceded":0,"big_chances_missed":0,"errors_leading_to_goal":0,"errors_leading_to_goal_attempt":0,"tackled":0,"offside":0,"target_missed":0,"fouls":0,"dribbles":0,"element":205,"fixture":213,"opponent_team":5},{"id":12310,"kickoff_time":"2019-01-20T13:30:00Z","kickoff_time_formatted":"20 Jan 13:30","team_h_score":0,"team_a_score":3,"was_home":true,"round":23,"total_points":0,"value":43,"transfers_balance":-99,"selected":2990,"transfers_in":57,"transfers_out":156,"loaned_in":0,"loaned_out":0,"minutes":0,"goals_scored":0,"assists":0,"clean_sheets":0,"goals_conceded":0,"own_goals":0,"penalties_saved":0,"penalties_missed":0,"yellow_cards":0,"red_cards":0,"saves":0,"bonus":0,"bps":0,"influence":"0.0","creativity":"0.0","threat":"0.0","ict_index":"0.0","ea_index":0,"open_play_crosses":0,"big_chances_created":0,"clearances_blocks_interceptions":0,"recoveries":0,"key_passes":0,"tackles":0,"winning_goals":0,"attempted_passes":0,"completed_passes":0,"penalties_conceded":0,"big_chances_missed":0,"errors_leading_to_goal":0,"errors_leading_to_goal_attempt":0,"tackled":0,"offside":0,"target_missed":0,"fouls":0,"dribbles":0,"element":205,"fixture":224,"opponent_team":13},{"id":12889,"kickoff_time":"2019-01-29T19:45:00Z","kickoff_time_formatted":"29 Jan 19:45","team_h_score":0,"team_a_score":1,"was_home":true,"round":24,"total_points":0,"value":43,"transfers_balance":-61,"selected":2928,"transfers_in":39,"transfers_out":100,"loaned_in":0,"loaned_out":0,"minutes":0,"goals_scored":0,"assists":0,"clean_sheets":0,"goals_conceded":0,"own_goals":0,"penalties_saved":0,"penalties_missed":0,"yellow_cards":0,"red_cards":0,"saves":0,"bonus":0,"bps":0,"influence":"0.0","creativity":"0.0","threat":"0.0","ict_index":"0.0","ea_index":0,"open_play_crosses":0,"big_chances_created":0,"clearances_blocks_interceptions":0,"recoveries":0,"key_passes":0,"tackles":0,"winning_goals":0,"attempted_passes":0,"completed_passes":0,"penalties_conceded":0,"big_chances_missed":0,"errors_leading_to_goal":0,"errors_leading_to_goal_attempt":0,"tackled":0,"offside":0,"target_missed":0,"fouls":0,"dribbles":0,"element":205,"fixture":234,"opponent_team":8},{"id":13495,"kickoff_time":"2019-02-02T15:00:00Z","kickoff_time_formatted":"02 Feb 15:00","team_h_score":5,"team_a_score":0,"was_home":false,"round":25,"total_points":0,"value":43,"transfers_balance":-31,"selected":2898,"transfers_in":14,"transfers_out":45,"loaned_in":0,"loaned_out":0,"minutes":0,"goals_scored":0,"assists":0,"clean_sheets":0,"goals_conceded":0,"own_goals":0,"penalties_saved":0,"penalties_missed":0,"yellow_cards":0,"red_cards":0,"saves":0,"bonus":0,"bps":0,"influence":"0.0","creativity":"0.0","threat":"0.0","ict_index":"0.0","ea_index":0,"open_play_crosses":0,"big_chances_created":0,"clearances_blocks_interceptions":0,"recoveries":0,"key_passes":0,"tackles":0,"winning_goals":0,"attempted_passes":0,"completed_passes":0,"penalties_conceded":0,"big_chances_missed":0,"errors_leading_to_goal":0,"errors_leading_to_goal_attempt":0,"tackled":0,"offside":0,"target_missed":0,"fouls":0,"dribbles":0,"element":205,"fixture":244,"opponent_team":6},{"id":14126,"kickoff_time":"2019-02-09T15:00:00Z","kickoff_time_formatted":"09 Feb 15:00","team_h_score":1,"team_a_score":2,"was_home":true,"round":26,"total_points":0,"value":43,"transfers_balance":23,"selected":2940,"transfers_in":90,"transfers_out":67,"loaned_in":0,"loaned_out":0,"minutes":0,"goals_scored":0,"assists":0,"clean_sheets":0,"goals_conceded":0,"own_goals":0,"penalties_saved":0,"penalties_missed":0,"yellow_cards":0,"red_cards":0,"saves":0,"bonus":0,"bps":0,"influence":"0.0","creativity":"0.0","threat":"0.0","ict_index":"0.0","ea_index":0,"open_play_crosses":0,"big_chances_created":0,"clearances_blocks_interceptions":0,"recoveries":0,"key_passes":0,"tackles":0,"winning_goals":0,"attempted_passes":0,"completed_passes":0,"penalties_conceded":0,"big_chances_missed":0,"errors_leading_to_goal":0,"errors_leading_to_goal_attempt":0,"tackled":0,"offside":0,"target_missed":0,"fouls":0,"dribbles":0,"element":205,"fixture":254,"opponent_team":1},{"id":14658,"kickoff_time":"2019-02-23T15:00:00Z","kickoff_time_formatted":"23 Feb 15:00","team_h_score":2,"team_a_score":0,"was_home":false,"round":27,"total_points":0,"value":43,"transfers_balance":7,"selected":2970,"transfers_in":69,"transfers_out":62,"loaned_in":0,"loaned_out":0,"minutes":0,"goals_scored":0,"assists":0,"clean_sheets":0,"goals_conceded":0,"own_goals":0,"penalties_saved":0,"penalties_missed":0,"yellow_cards":0,"red_cards":0,"saves":0,"bonus":0,"bps":0,"influence":"0.0","creativity":"0.0","threat":"0.0","ict_index":"0.0","ea_index":0,"open_play_crosses":0,"big_chances_created":0,"clearances_blocks_interceptions":0,"recoveries":0,"key_passes":0,"tackles":0,"winning_goals":0,"attempted_passes":0,"completed_passes":0,"penalties_conceded":0,"big_chances_missed":0,"errors_leading_to_goal":0,"errors_leading_to_goal_attempt":0,"tackled":0,"offside":0,"target_missed":0,"fouls":0,"dribbles":0,"element":205,"fixture":269,"opponent_team":15},{"id":15210,"kickoff_time":"2019-02-26T19:45:00Z","kickoff_time_formatted":"26 Feb 19:45","team_h_score":1,"team_a_score":0,"was_home":true,"round":28,"total_points":0,"value":43,"transfers_balance":-11,"selected":2942,"transfers_in":19,"transfers_out":30,"loaned_in":0,"loaned_out":0,"minutes":0,"goals_scored":0,"assists":0,"clean_sheets":0,"goals_conceded":0,"own_goals":0,"penalties_saved":0,"penalties_missed":0,"yellow_cards":0,"red_cards":0,"saves":0,"bonus":0,"bps":0,"influence":"0.0","creativity":"0.0","threat":"0.0","ict_index":"0.0","ea_index":0,"open_play_crosses":0,"big_chances_created":0,"clearances_blocks_interceptions":0,"recoveries":0,"key_passes":0,"tackles":0,"winning_goals":0,"attempted_passes":0,"completed_passes":0,"penalties_conceded":0,"big_chances_missed":0,"errors_leading_to_goal":0,"errors_leading_to_goal_attempt":0,"tackled":0,"offside":0,"target_missed":0,"fouls":0,"dribbles":0,"element":205,"fixture":274,"opponent_team":20},{"id":15815,"kickoff_time":"2019-03-02T15:00:00Z","kickoff_time_formatted":"02 Mar 15:00","team_h_score":1,"team_a_score":0,"was_home":false,"round":29,"total_points":0,"value":43,"transfers_balance":-13,"selected":2935,"transfers_in":38,"transfers_out":51,"loaned_in":0,"loaned_out":0,"minutes":0,"goals_scored":0,"assists":0,"clean_sheets":0,"goals_conceded":0,"own_goals":0,"penalties_saved":0,"penalties_missed":0,"yellow_cards":0,"red_cards":0,"saves":0,"bonus":0,"bps":0,"influence":"0.0","creativity":"0.0","threat":"0.0","ict_index":"0.0","ea_index":0,"open_play_crosses":0,"big_chances_created":0,"clearances_blocks_interceptions":0,"recoveries":0,"key_passes":0,"tackles":0,"winning_goals":0,"attempted_passes":0,"completed_passes":0,"penalties_conceded":0,"big_chances_missed":0,"errors_leading_to_goal":0,"errors_leading_to_goal_attempt":0,"tackled":0,"offside":0,"target_missed":0,"fouls":0,"dribbles":0,"element":205,"fixture":282,"opponent_team":3},{"id":16421,"kickoff_time":"2019-03-09T15:00:00Z","kickoff_time_formatted":"09 Mar 15:00","team_h_score":0,"team_a_score":2,"was_home":true,"round":30,"total_points":0,"value":43,"transfers_balance":-17,"selected":2922,"transfers_in":39,"transfers_out":56,"loaned_in":0,"loaned_out":0,"minutes":0,"goals_scored":0,"assists":0,"clean_sheets":0,"goals_conceded":0,"own_goals":0,"penalties_saved":0,"penalties_missed":0,"yellow_cards":0,"red_cards":0,"saves":0,"bonus":0,"bps":0,"influence":"0.0","creativity":"0.0","threat":"0.0","ict_index":"0.0","ea_index":0,"open_play_crosses":0,"big_chances_created":0,"clearances_blocks_interceptions":0,"recoveries":0,"key_passes":0,"tackles":0,"winning_goals":0,"attempted_passes":0,"completed_passes":0,"penalties_conceded":0,"big_chances_missed":0,"errors_leading_to_goal":0,"errors_leading_to_goal_attempt":0,"tackled":0,"offside":0,"target_missed":0,"fouls":0,"dribbles":0,"element":205,"fixture":295,"opponent_team":2},{"id":16943,"kickoff_time":"2019-03-16T15:00:00Z","kickoff_time_formatted":"16 Mar 15:00","team_h_score":4,"team_a_score":3,"was_home":false,"round":31,"total_points":0,"value":43,"transfers_balance":-7,"selected":3014,"transfers_in":36,"transfers_out":43,"loaned_in":0,"loaned_out":0,"minutes":0,"goals_scored":0,"assists":0,"clean_sheets":0,"goals_conceded":0,"own_goals":0,"penalties_saved":0,"penalties_missed":0,"yellow_cards":0,"red_cards":0,"saves":0,"bonus":0,"bps":0,"influence":"0.0","creativity":"0.0","threat":"0.0","ict_index":"0.0","ea_index":0,"open_play_crosses":0,"big_chances_created":0,"clearances_blocks_interceptions":0,"recoveries":0,"key_passes":0,"tackles":0,"winning_goals":0,"attempted_passes":0,"completed_passes":0,"penalties_conceded":0,"big_chances_missed":0,"errors_leading_to_goal":0,"errors_leading_to_goal_attempt":0,"tackled":0,"offside":0,"target_missed":0,"fouls":0,"dribbles":0,"element":205,"fixture":309,"opponent_team":19},{"id":17435,"kickoff_time":"2019-03-30T15:00:00Z","kickoff_time_formatted":"30 Mar 15:00","team_h_score":2,"team_a_score":0,"was_home":false,"round":32,"total_points":0,"value":43,"transfers_balance":65,"selected":3157,"transfers_in":141,"transfers_out":76,"loaned_in":0,"loaned_out":0,"minutes":0,"goals_scored":0,"assists":0,"clean_sheets":0,"goals_conceded":0,"own_goals":0,"penalties_saved":0,"penalties_missed":0,"yellow_cards":0,"red_cards":0,"saves":0,"bonus":0,"bps":0,"influence":"0.0","creativity":"0.0","threat":"0.0","ict_index":"0.0","ea_index":0,"open_play_crosses":0,"big_chances_created":0,"clearances_blocks_interceptions":0,"recoveries":0,"key_passes":0,"tackles":0,"winning_goals":0,"attempted_passes":0,"completed_passes":0,"penalties_conceded":0,"big_chances_missed":0,"errors_leading_to_goal":0,"errors_leading_to_goal_attempt":0,"tackled":0,"offside":0,"target_missed":0,"fouls":0,"dribbles":0,"element":205,"fixture":315,"opponent_team":7},{"id":18179,"kickoff_time":"2019-04-06T14:00:00Z","kickoff_time_formatted":"06 Apr 15:00","team_h_score":1,"team_a_score":4,"was_home":true,"round":33,"total_points":0,"value":43,"transfers_balance":-16,"selected":3004,"transfers_in":32,"transfers_out":48,"loaned_in":0,"loaned_out":0,"minutes":0,"goals_scored":0,"assists":0,"clean_sheets":0,"goals_conceded":0,"own_goals":0,"penalties_saved":0,"penalties_missed":0,"yellow_cards":0,"red_cards":0,"saves":0,"bonus":0,"bps":0,"influence":"0.0","creativity":"0.0","threat":"0.0","ict_index":"0.0","ea_index":0,"open_play_crosses":0,"big_chances_created":0,"clearances_blocks_interceptions":0,"recoveries":0,"key_passes":0,"tackles":0,"winning_goals":0,"attempted_passes":0,"completed_passes":0,"penalties_conceded":0,"big_chances_missed":0,"errors_leading_to_goal":0,"errors_leading_to_goal_attempt":0,"tackled":0,"offside":0,"target_missed":0,"fouls":0,"dribbles":0,"element":205,"fixture":324,"opponent_team":11},{"id":18656,"kickoff_time":"2019-04-13T11:30:00Z","kickoff_time_formatted":"13 Apr 12:30","team_h_score":4,"team_a_score":0,"was_home":false,"round":34,"total_points":0,"value":43,"transfers_balance":-39,"selected":2941,"transfers_in":29,"transfers_out":68,"loaned_in":0,"loaned_out":0,"minutes":0,"goals_scored":0,"assists":0,"clean_sheets":0,"goals_conceded":0,"own_goals":0,"penalties_saved":0,"penalties_missed":0,"yellow_cards":0,"red_cards":0,"saves":0,"bonus":0,"bps":0,"influence":"0.0","creativity":"0.0","threat":"0.0","ict_index":"0.0","ea_index":0,"open_play_crosses":0,"big_chances_created":0,"clearances_blocks_interceptions":0,"recoveries":0,"key_passes":0,"tackles":0,"winning_goals":0,"attempted_passes":0,"completed_passes":0,"penalties_conceded":0,"big_chances_missed":0,"errors_leading_to_goal":0,"errors_leading_to_goal_attempt":0,"tackled":0,"offside":0,"target_missed":0,"fouls":0,"dribbles":0,"element":205,"fixture":339,"opponent_team":17},{"id":19326,"kickoff_time":"2019-04-20T14:00:00Z","kickoff_time_formatted":"20 Apr 15:00","team_h_score":1,"team_a_score":2,"was_home":true,"round":35,"total_points":0,"value":43,"transfers_balance":-34,"selected":2901,"transfers_in":16,"transfers_out":50,"loaned_in":0,"loaned_out":0,"minutes":0,"goals_scored":0,"assists":0,"clean_sheets":0,"goals_conceded":0,"own_goals":0,"penalties_saved":0,"penalties_missed":0,"yellow_cards":0,"red_cards":0,"saves":0,"bonus":0,"bps":0,"influence":"0.0","creativity":"0.0","threat":"0.0","ict_index":"0.0","ea_index":0,"open_play_crosses":0,"big_chances_created":0,"clearances_blocks_interceptions":0,"recoveries":0,"key_passes":0,"tackles":0,"winning_goals":0,"attempted_passes":0,"completed_passes":0,"penalties_conceded":0,"big_chances_missed":0,"errors_leading_to_goal":0,"errors_leading_to_goal_attempt":0,"tackled":0,"offside":0,"target_missed":0,"fouls":0,"dribbles":0,"element":205,"fixture":346,"opponent_team":18},{"id":20141,"kickoff_time":"2019-04-26T19:00:00Z","kickoff_time_formatted":"26 Apr 20:00","team_h_score":5,"team_a_score":0,"was_home":false,"round":36,"total_points":0,"value":43,"transfers_balance":-14,"selected":2895,"transfers_in":18,"transfers_out":32,"loaned_in":0,"loaned_out":0,"minutes":0,"goals_scored":0,"assists":0,"clean_sheets":0,"goals_conceded":0,"own_goals":0,"penalties_saved":0,"penalties_missed":0,"yellow_cards":0,"red_cards":0,"saves":0,"bonus":0,"bps":0,"influence":"0.0","creativity":"0.0","threat":"0.0","ict_index":"0.0","ea_index":0,"open_play_crosses":0,"big_chances_created":0,"clearances_blocks_interceptions":0,"recoveries":0,"key_passes":0,"tackles":0,"winning_goals":0,"attempted_passes":0,"completed_passes":0,"penalties_conceded":0,"big_chances_missed":0,"errors_leading_to_goal":0,"errors_leading_to_goal_attempt":0,"tackled":0,"offside":0,"target_missed":0,"fouls":0,"dribbles":0,"element":205,"fixture":356,"opponent_team":12},{"id":20756,"kickoff_time":"2019-05-05T13:00:00Z","kickoff_time_formatted":"05 May 14:00","team_h_score":1,"team_a_score":1,"was_home":true,"round":37,"total_points":0,"value":43,"transfers_balance":1,"selected":2893,"transfers_in":45,"transfers_out":44,"loaned_in":0,"loaned_out":0,"minutes":0,"goals_scored":0,"assists":0,"clean_sheets":0,"goals_conceded":0,"own_goals":0,"penalties_saved":0,"penalties_missed":0,"yellow_cards":0,"red_cards":0,"saves":0,"bonus":0,"bps":0,"influence":"0.0","creativity":"0.0","threat":"0.0","ict_index":"0.0","ea_index":0,"open_play_crosses":0,"big_chances_created":0,"clearances_blocks_interceptions":0,"recoveries":0,"key_passes":0,"tackles":0,"winning_goals":0,"attempted_passes":0,"completed_passes":0,"penalties_conceded":0,"big_chances_missed":0,"errors_leading_to_goal":0,"errors_leading_to_goal_attempt":0,"tackled":0,"offside":0,"target_missed":0,"fouls":0,"dribbles":0,"element":205,"fixture":366,"opponent_team":14},{"id":21372,"kickoff_time":"2019-05-12T14:00:00Z","kickoff_time_formatted":"12 May 15:00","team_h_score":1,"team_a_score":1,"was_home":false,"round":38,"total_points":0,"value":43,"transfers_balance":13,"selected":2914,"transfers_in":55,"transfers_out":42,"loaned_in":0,"loaned_out":0,"minutes":0,"goals_scored":0,"assists":0,"clean_sheets":0,"goals_conceded":0,"own_goals":0,"penalties_saved":0,"penalties_missed":0,"yellow_cards":0,"red_cards":0,"saves":0,"bonus":0,"bps":0,"influence":"0.0","creativity":"0.0","threat":"0.0","ict_index":"0.0","ea_index":0,"open_play_crosses":0,"big_chances_created":0,"clearances_blocks_interceptions":0,"recoveries":0,"key_passes":0,"tackles":0,"winning_goals":0,"attempted_passes":0,"completed_passes":0,"penalties_conceded":0,"big_chances_missed":0,"errors_leading_to_goal":0,"errors_leading_to_goal_attempt":0,"tackled":0,"offside":0,"target_missed":0,"fouls":0,"dribbles":0,"element":205,"fixture":378,"opponent_team":16}]}