{"history_past":[{"id":3026,"season_name":"2010/11","element_code":43020,"start_cost":75,"end_cost":71,"total_points":110,"minutes":1491,"goals_scored":13,"assists":2,"clean_sheets":4,"goals_conceded":12,"own_goals":0,"penalties_saved":0,"penalties_missed":0,"yellow_cards":5,"red_cards":0,"saves":0,"bonus":16,"bps":0,"influence":"0.0","creativity":"0.0","threat":"0.0","ict_index":"0.0","ea_index":0,"season":5},{"id":3892,"season_name":"2011/12","element_code":43020,"start_cost":100,"end_cost":99,"total_points":106,"minutes":1477,"goals_scored":10,"assists":2,"clean_sheets":12,"goals_conceded":11,"own_goals":0,"penalties_saved":0,"penalties_missed":0,"yellow_cards":0,"red_cards":0,"saves":0,"bonus":18,"bps":0,"influence":"0.0","creativity":"0.0","threat":"0.0","ict_index":"0.0","ea_index":344,"season":6},{"id":4601,"season_name":"2012/13","element_code":43020,"start_cost":80,"end_cost":65,"total_points":92,"minutes":953,"goals_scored":10,"assists":5,"clean_sheets":5,"goals_conceded":11,"own_goals":0,"penalties_saved":0,"penalties_missed":1,"yellow_cards":1,"red_cards":0,"saves":0,"bonus":9,"bps":0,"influence":"0.0","creativity":"0.0","threat":"0.0","ict_index":"0.0","ea_index":302,"season":7},{"id":5296,"season_name":"2013/14","element_code":43020,"start_cost":75,"end_cost":70,"total_points":56,"minutes":854,"goals_scored":4,"assists":3,"clean_sheets":2,"goals_conceded":9,"own_goals":0,"penalties_saved":0,"penalties_missed":0,"yellow_cards":2,"red_cards":0,"saves":0,"bonus":4,"bps":71,"influence":"0.0","creativity":"0.0","threat":"0.0","ict_index":"0.0","ea_index":195,"season":8},{"id":6015,"season_name":"2014/15","element_code":43020,"start_cost":60,"end_cost":59,"total_points":1,"minutes":45,"goals_scored":0,"assists":0,"clean_sheets":0,"goals_conceded":1,"own_goals":0,"penalties_saved":0,"penalties_missed":0,"yellow_cards":0,"red_cards":0,"saves":0,"bonus":0,"bps":2,"influence":"0.0","creativity":"0.0","threat":"0.0","ict_index":"0.0","ea_index":3,"season":9},{"id":6728,"season_name":"2015/16","element_code":43020,"start_cost":60,"end_cost":60,"total_points":1,"minutes":24,"goals_scored":0,"assists":0,"clean_sheets":0,"goals_conceded":0,"own_goals":0,"penalties_saved":0,"penalties_missed":0,"yellow_cards":0,"red_cards":0,"saves":0,"bonus":0,"bps":1,"influence":"0.0","creativity":"0.0","threat":"0.0","ict_index":"0.0","ea_index":7,"season":10},{"id":8121,"season_name":"2017/18","element_code":43020,"start_cost":70,"end_cost":67,"total_points":93,"minutes":1537,"goals_scored":8,"assists":2,"clean_sheets":6,"goals_conceded":36,"own_goals":0,"penalties_saved":0,"penalties_missed":0,"yellow_cards":3,"red_cards":0,"saves":0,"bonus":14,"bps":309,"influence":"373.6","creativity":"312.4","threat":"476.0","ict_index":"115.0","ea_index":0,"season":12}],"fixtures_summary":[],"explain":[{"explain":{"minutes":{"points":0,"name":"Minutes played","value":0}},"fixture":{"id":380,"kickoff_time_formatted":"12 May 15:00","started":true,"event_day":1,"deadline_time":"2019-05-12T13:00:00Z","deadline_time_formatted":"12 May 14:00","stats":[{"goals_scored":{"a":[{"value":2,"element":411},{"value":1,"element":414},{"value":1,"element":417}],"h":[{"value":1,"element":394}]}},{"assists":{"a":[{"value":3,"element":415},{"value":1,"element":465}],"h":[]}},{"own_goals":{"a":[],"h":[]}},{"penalties_saved":{"a":[],"h":[]}},{"penalties_missed":{"a":[],"h":[]}},{"yellow_cards":{"a":[],"h":[{"value":1,"element":389}]}},{"red_cards":{"a":[],"h":[{"value":1,"element":378}]}},{"saves":{"a":[{"value":7,"element":400}],"h":[{"value":5,"element":445}]}},{"bonus":{"a":[{"value":3,"element":411},{"value":2,"element":415},{"value":1,"element":414}],"h":[]}},{"bps":{"a":[{"value":54,"element":411},{"value":38,"element":415},{"value":37,"element":414},{"value":25,"element":400},{"value":23,"element":417},{"value":23,"element":465},{"value":19,"element":410},{"value":17,"element":464},{"value":14,"element":409},{"value":13,"element":406},{"value":7,"element":405},{"value":6,"element":447},{"value":3,"element":518},{"value":2,"element":408}],"h":[{"value":20,"element":445},{"value":19,"element":390},{"value":15,"element":376},{"value":15,"element":380},{"value":15,"element":394},{"value":11,"element":391},{"value":10,"element":389},{"value":9,"element":392},{"value":4,"element":382},{"value":4,"element":383},{"value":3,"element":386},{"value":3,"element":396},{"value":2,"element":395},{"value":-2,"element":378}]}}],"code":987971,"kickoff_time":"2019-05-12T14:00:00Z","team_h_score":1,"team_a_score":4,"finished":true,"minutes":90,"provisional_start_time":false,"finished_provisional":true,"event":38,"team_a":19,"team_h":18}}],"history_summary":[{"id":20355,"kickoff_time":"2019-04-27T11:30:00Z","kickoff_time_formatted":"27 Apr 12:30","team_h_score":0,"team_a_score":1,"was_home":false,"round":36,"total_points":0,"value":61,"transfers_balance":-5031,"selected":93401,"transfers_in":73,"transfers_out":5104,"loaned_in":0,"loaned_out":0,"minutes":0,"goals_scored":0,"assists":0,"clean_sheets":0,"goals_conceded":0,"own_goals":0,"penalties_saved":0,"penalties_missed":0,"yellow_cards":0,"red_cards":0,"saves":0,"bonus":0,"bps":0,"influence":"0.0","creativity":"0.0","threat":"0.0","ict_index":"0.0","ea_index":0,"open_play_crosses":0,"big_chances_created":0,"clearances_blocks_interceptions":0,"recoveries":0,"key_passes":0,"tackles":0,"winning_goals":0,"attempted_passes":0,"completed_passes":0,"penalties_conceded":0,"big_chances_missed":0,"errors_leading_to_goal":0,"errors_leading_to_goal_attempt":0,"tackled":0,"offside":0,"target_missed":0,"fouls":0,"dribbles":0,"element":419,"fixture":359,"opponent_team":17},{"id":20970,"kickoff_time":"2019-05-04T14:00:00Z","kickoff_time_formatted":"04 May 15:00","team_h_score":3,"team_a_score":0,"was_home":true,"round":37,"total_points":0,"value":61,"transfers_balance":371,"selected":94074,"transfers_in":2495,"transfers_out":2124,"loaned_in":0,"loaned_out":0,"minutes":0,"goals_scored":0,"assists":0,"clean_sheets":0,"goals_conceded":0,"own_goals":0,"penalties_saved":0,"penalties_missed":0,"yellow_cards":0,"red_cards":0,"saves":0,"bonus":0,"bps":0,"influence":"0.0","creativity":"0.0","threat":"0.0","ict_index":"0.0","ea_index":0,"open_play_crosses":0,"big_chances_created":0,"clearances_blocks_interceptions":0,"recoveries":0,"key_passes":0,"tackles":0,"winning_goals":0,"attempted_passes":0,"completed_passes":0,"penalties_conceded":0,"big_chances_missed":0,"errors_leading_to_goal":0,"errors_leading_to_goal_attempt":0,"tackled":0,"offside":0,"target_missed":0,"fouls":0,"dribbles":0,"element":419,"fixture":369,"opponent_team":16},{"id":21586,"kickoff_time":"2019-05-12T14:00:00Z","kickoff_time_formatted":"12 May 15:00","team_h_score":1,"team_a_score":4,"was_home":false,"round":38,"total_points":0,"value":61,"transfers_balance":-2237,"selected":91700,"transfers_in":505,"transfers_out":2742,"loaned_in":0,"loaned_out":0,"minutes":0,"goals_scored":0,"assists":0,"clean_sheets":0,"goals_conceded":0,"own_goals":0,"penalties_saved":0,"penalties_missed":0,"yellow_cards":0,"red_cards":0,"saves":0,"bonus":0,"bps":0,"influence":"0.0","creativity":"0.0","threat":"0.0","ict_index":"0.0","ea_index":0,"open_play_crosses":0,"big_chances_created":0,"clearances_blocks_interceptions":0,"recoveries":0,"key_passes":0,"tackles":0,"winning_goals":0,"attempted_passes":0,"completed_passes":0,"penalties_conceded":0,"big_chances_missed":0,"errors_leading_to_goal":0,"errors_leading_to_goal_attempt":0,"tackled":0,"offside":0,"target_missed":0,"fouls":0,"dribbles":0,"element":419,"fixture":380,"opponent_team":18}],"fixtures":[],"history":[{"id":419,"kickoff_time":"2018-08-12T12:30:00Z","kickoff_time_formatted":"12 Aug 13:30","team_h_score":4,"team_a_score":0,"was_home":false,"round":1,"total_points":1,"value":65,"transfers_balance":0,"selected":118570,"transfers_in":0,"transfers_out":0,"loaned_in":0,"loaned_out":0,"minutes":28,"goals_scored":0,"assists":0,"clean_sheets":0,"goals_conceded":1,"own_goals":0,"penalties_saved":0,"penalties_missed":0,"yellow_cards":0,"red_cards":0,"saves":0,"bonus":0,"bps":3,"influence":"0.0","creativity":"0.0","threat":"0.0","ict_index":"0.0","ea_index":0,"open_play_crosses":0,"big_chances_created":0,"clearances_blocks_interceptions":0,"recoveries":0,"key_passes":0,"tackles":0,"winning_goals":0,"attempted_passes":4,"completed_passes":2,"penalties_conceded":0,"big_chances_missed":0,"errors_leading_to_goal":0,"errors_leading_to_goal_attempt":0,"tackled":0,"offside":0,"target_missed":0,"fouls":0,"dribbles":0,"element":419,"fixture":5,"opponent_team":12},{"id":944,"kickoff_time":"2018-08-18T14:00:00Z","kickoff_time_formatted":"18 Aug 15:00","team_h_score":1,"team_a_score":2,"was_home":true,"round":2,"total_points":5,"value":65,"transfers_balance":-12977,"selected":120170,"transfers_in":4164,"transfers_out":17141,"loaned_in":0,"loaned_out":0,"minutes":66,"goals_scored":0,"assists":1,"clean_sheets":0,"goals_conceded":2,"own_goals":0,"penalties_saved":0,"penalties_missed":0,"yellow_cards":0,"red_cards":0,"saves":0,"bonus":0,"bps":15,"influence":"4.0","creativity":"4.0","threat":"40.0","ict_index":"4.8","ea_index":0,"open_play_crosses":0,"big_chances_created":0,"clearances_blocks_interceptions":0,"recoveries":3,"key_passes":0,"tackles":0,"winning_goals":0,"attempted_passes":17,"completed_passes":14,"penalties_conceded":0,"big_chances_missed":0,"errors_leading_to_goal":0,"errors_leading_to_goal_attempt":0,"tackled":0,"offside":0,"target_missed":1,"fouls":0,"dribbles":0,"element":419,"fixture":20,"opponent_team":2},{"id":1471,"kickoff_time":"2018-08-25T14:00:00Z","kickoff_time_formatted":"25 Aug 15:00","team_h_score":3,"team_a_score":1,"was_home":false,"round":3,"total_points":1,"value":65,"transfers_balance":-8490,"selected":117891,"transfers_in":6330,"transfers_out":14820,"loaned_in":0,"loaned_out":0,"minutes":31,"goals_scored":0,"assists":0,"clean_sheets":0,"goals_conceded":2,"own_goals":0,"penalties_saved":0,"penalties_missed":0,"yellow_cards":0,"red_cards":0,"saves":0,"bonus":0,"bps":0,"influence":"0.2","creativity":"1.3","threat":"8.0","ict_index":"1.0","ea_index":0,"open_play_crosses":0,"big_chances_created":0,"clearances_blocks_interceptions":1,"recoveries":1,"key_passes":0,"tackles":0,"winning_goals":0,"attempted_passes":10,"completed_passes":8,"penalties_conceded":0,"big_chances_missed":0,"errors_leading_to_goal":0,"errors_leading_to_goal_attempt":0,"tackled":1,"offside":1,"target_missed":1,"fouls":0,"dribbles":0,"element":419,"fixture":21,"opponent_team":1},{"id":2002,"kickoff_time":"2018-09-01T14:00:00Z","kickoff_time_formatted":"01 Sep 15:00","team_h_score":0,"team_a_score":1,"was_home":true,"round":4,"total_points":1,"value":64,"transfers_balance":-15224,"selected":105324,"transfers_in":3863,"transfers_out":19087,"loaned_in":0,"loaned_out":0,"minutes":15,"goals_scored":0,"assists":0,"clean_sheets":0,"goals_conceded":1,"own_goals":0,"penalties_saved":0,"penalties_missed":0,"yellow_cards":0,"red_cards":0,"saves":0,"bonus":0,"bps":6,"influence":"2.4","creativity":"10.0","threat":"0.0","ict_index":"1.2","ea_index":0,"open_play_crosses":0,"big_chances_created":1,"clearances_blocks_interceptions":0,"recoveries":0,"key_passes":1,"tackles":0,"winning_goals":0,"attempted_passes":5,"completed_passes":5,"penalties_conceded":0,"big_chances_missed":0,"errors_leading_to_goal":0,"errors_leading_to_goal_attempt":0,"tackled":1,"offside":0,"target_missed":0,"fouls":0,"dribbles":0,"element":419,"fixture":40,"opponent_team":20},{"id":2539,"kickoff_time":"2018-09-16T15:00:00Z","kickoff_time_formatted":"16 Sep 16:00","team_h_score":1,"team_a_score":3,"was_home":false,"round":5,"total_points":0,"value":64,"transfers_balance":-17315,"selected":90038,"transfers_in":2031,"transfers_out":19346,"loaned_in":0,"loaned_out":0,"minutes":0,"goals_scored":0,"assists":0,"clean_sheets":0,"goals_conceded":0,"own_goals":0,"penalties_saved":0,"penalties_missed":0,"yellow_cards":0,"red_cards":0,"saves":0,"bonus":0,"bps":0,"influence":"0.0","creativity":"0.0","threat":"0.0","ict_index":"0.0","ea_index":0,"open_play_crosses":0,"big_chances_created":0,"clearances_blocks_interceptions":0,"recoveries":0,"key_passes":0,"tackles":0,"winning_goals":0,"attempted_passes":0,"completed_passes":0,"penalties_conceded":0,"big_chances_missed":0,"errors_leading_to_goal":0,"errors_leading_to_goal_attempt":0,"tackled":0,"offside":0,"target_missed":0,"fouls":0,"dribbles":0,"element":419,"fixture":43,"opponent_team":8},{"id":3076,"kickoff_time":"2018-09-23T12:30:00Z","kickoff_time_formatted":"23 Sep 13:30","team_h_score":0,"team_a_score":0,"was_home":true,"round":6,"total_points":0,"value":63,"transfers_balance":-14255,"selected":76267,"transfers_in":185,"transfers_out":14440,"loaned_in":0,"loaned_out":0,"minutes":0,"goals_scored":0,"assists":0,"clean_sheets":0,"goals_conceded":0,"own_goals":0,"penalties_saved":0,"penalties_missed":0,"yellow_cards":0,"red_cards":0,"saves":0,"bonus":0,"bps":0,"influence":"0.0","creativity":"0.0","threat":"0.0","ict_index":"0.0","ea_index":0,"open_play_crosses":0,"big_chances_created":0,"clearances_blocks_interceptions":0,"recoveries":0,"key_passes":0,"tackles":0,"winning_goals":0,"attempted_passes":0,"completed_passes":0,"penalties_conceded":0,"big_chances_missed":0,"errors_leading_to_goal":0,"errors_leading_to_goal_attempt":0,"tackled":0,"offside":0,"target_missed":0,"fouls":0,"dribbles":0,"element":419,"fixture":60,"opponent_team":6},{"id":3614,"kickoff_time":"2018-09-29T11:30:00Z","kickoff_time_formatted":"29 Sep 12:30","team_h_score":3,"team_a_score":1,"was_home":true,"round":7,"total_points":0,"value":63,"transfers_balance":-8307,"selected":68379,"transfers_in":105,"transfers_out":8412,"loaned_in":0,"loaned_out":0,"minutes":0,"goals_scored":0,"assists":0,"clean_sheets":0,"goals_conceded":0,"own_goals":0,"penalties_saved":0,"penalties_missed":0,"yellow_cards":0,"red_cards":0,"saves":0,"bonus":0,"bps":0,"influence":"0.0","creativity":"0.0","threat":"0.0","ict_index":"0.0","ea_index":0,"open_play_crosses":0,"big_chances_created":0,"clearances_blocks_interceptions":0,"recoveries":0,"key_passes":0,"tackles":0,"winning_goals":0,"attempted_passes":0,"completed_passes":0,"penalties_conceded":0,"big_chances_missed":0,"errors_leading_to_goal":0,"errors_leading_to_goal_attempt":0,"tackled":0,"offside":0,"target_missed":0,"fouls":0,"dribbles":0,"element":419,"fixture":69,"opponent_team":14},{"id":4153,"kickoff_time":"2018-10-05T19:00:00Z","kickoff_time_formatted":"05 Oct 20:00","team_h_score":1,"team_a_score":0,"was_home":false,"round":8,"total_points":0,"value":62,"transfers_balance":-4486,"selected":64130,"transfers_in":72,"transfers_out":4558,"loaned_in":0,"loaned_out":0,"minutes":0,"goals_scored":0,"assists":0,"clean_sheets":0,"goals_conceded":0,"own_goals":0,"penalties_saved":0,"penalties_missed":0,"yellow_cards":0,"red_cards":0,"saves":0,"bonus":0,"bps":0,"influence":"0.0","creativity":"0.0","threat":"0.0","ict_index":"0.0","ea_index":0,"open_play_crosses":0,"big_chances_created":0,"clearances_blocks_interceptions":0,"recoveries":0,"key_passes":0,"tackles":0,"winning_goals":0,"attempted_passes":0,"completed_passes":0,"penalties_conceded":0,"big_chances_missed":0,"errors_leading_to_goal":0,"errors_leading_to_goal_attempt":0,"tackled":0,"offside":0,"target_missed":0,"fouls":0,"dribbles":0,"element":419,"fixture":71,"opponent_team":3},{"id":4695,"kickoff_time":"2018-10-20T14:00:00Z","kickoff_time_formatted":"20 Oct 15:00","team_h_score":0,"team_a_score":1,"was_home":true,"round":9,"total_points":1,"value":62,"transfers_balance":-3533,"selected":60924,"transfers_in":256,"transfers_out":3789,"loaned_in":0,"loaned_out":0,"minutes":33,"goals_scored":0,"assists":0,"clean_sheets":0,"goals_conceded":0,"own_goals":0,"penalties_saved":0,"penalties_missed":0,"yellow_cards":0,"red_cards":0,"saves":0,"bonus":0,"bps":3,"influence":"0.6","creativity":"4.7","threat":"0.0","ict_index":"0.5","ea_index":0,"open_play_crosses":0,"big_chances_created":0,"clearances_blocks_interceptions":0,"recoveries":0,"key_passes":0,"tackles":0,"winning_goals":0,"attempted_passes":6,"completed_passes":4,"penalties_conceded":0,"big_chances_missed":0,"errors_leading_to_goal":0,"errors_leading_to_goal_attempt":0,"tackled":0,"offside":0,"target_missed":0,"fouls":0,"dribbles":0,"element":419,"fixture":89,"opponent_team":17},{"id":5241,"kickoff_time":"2018-10-27T16:30:00Z","kickoff_time_formatted":"27 Oct 17:30","team_h_score":1,"team_a_score":1,"was_home":false,"round":10,"total_points":2,"value":62,"transfers_balance":-515,"selected":60745,"transfers_in":696,"transfers_out":1211,"loaned_in":0,"loaned_out":0,"minutes":60,"goals_scored":0,"assists":0,"clean_sheets":1,"goals_conceded":0,"own_goals":0,"penalties_saved":0,"penalties_missed":0,"yellow_cards":0,"red_cards":0,"saves":0,"bonus":0,"bps":4,"influence":"5.4","creativity":"0.7","threat":"2.0","ict_index":"0.8","ea_index":0,"open_play_crosses":0,"big_chances_created":0,"clearances_blocks_interceptions":1,"recoveries":0,"key_passes":0,"tackles":0,"winning_goals":0,"attempted_passes":12,"completed_passes":10,"penalties_conceded":0,"big_chances_missed":0,"errors_leading_to_goal":0,"errors_leading_to_goal_attempt":0,"tackled":2,"offside":0,"target_missed":0,"fouls":1,"dribbles":1,"element":419,"fixture":95,"opponent_team":11},{"id":5789,"kickoff_time":"2018-11-03T15:00:00Z","kickoff_time_formatted":"03 Nov 15:00","team_h_score":4,"team_a_score":2,"was_home":true,"round":11,"total_points":6,"value":62,"transfers_balance":617,"selected":61769,"transfers_in":2150,"transfers_out":1533,"loaned_in":0,"loaned_out":0,"minutes":29,"goals_scored":1,"assists":0,"clean_sheets":0,"goals_conceded":1,"own_goals":0,"penalties_saved":0,"penalties_missed":0,"yellow_cards":0,"red_cards":0,"saves":0,"bonus":1,"bps":27,"influence":"35.6","creativity":"10.5","threat":"35.0","ict_index":"8.1","ea_index":0,"open_play_crosses":0,"big_chances_created":0,"clearances_blocks_interceptions":0,"recoveries":1,"key_passes":1,"tackles":0,"winning_goals":0,"attempted_passes":7,"completed_passes":6,"penalties_conceded":0,"big_chances_missed":0,"errors_leading_to_goal":0,"errors_leading_to_goal_attempt":0,"tackled":0,"offside":1,"target_missed":0,"fouls":0,"dribbles":0,"element":419,"fixture":109,"opponent_team":4},{"id":6339,"kickoff_time":"2018-11-10T15:00:00Z","kickoff_time_formatted":"10 Nov 15:00","team_h_score":1,"team_a_score":1,"was_home":false,"round":12,"total_points":1,"value":62,"transfers_balance":1322,"selected":63482,"transfers_in":2749,"transfers_out":1427,"loaned_in":0,"loaned_out":0,"minutes":45,"goals_scored":0,"assists":0,"clean_sheets":0,"goals_conceded":0,"own_goals":0,"penalties_saved":0,"penalties_missed":0,"yellow_cards":0,"red_cards":0,"saves":0,"bonus":0,"bps":-6,"influence":"3.4","creativity":"1.4","threat":"44.0","ict_index":"4.9","ea_index":0,"open_play_crosses":0,"big_chances_created":0,"clearances_blocks_interceptions":1,"recoveries":2,"key_passes":0,"tackles":0,"winning_goals":0,"attempted_passes":13,"completed_passes":7,"penalties_conceded":0,"big_chances_missed":2,"errors_leading_to_goal":0,"errors_leading_to_goal_attempt":0,"tackled":1,"offside":1,"target_missed":1,"fouls":0,"dribbles":0,"element":419,"fixture":115,"opponent_team":10},{"id":6891,"kickoff_time":"2018-11-24T15:00:00Z","kickoff_time_formatted":"24 Nov 15:00","team_h_score":0,"team_a_score":4,"was_home":true,"round":13,"total_points":1,"value":62,"transfers_balance":-1059,"selected":62767,"transfers_in":1116,"transfers_out":2175,"loaned_in":0,"loaned_out":0,"minutes":35,"goals_scored":0,"assists":0,"clean_sheets":0,"goals_conceded":1,"own_goals":0,"penalties_saved":0,"penalties_missed":0,"yellow_cards":0,"red_cards":0,"saves":0,"bonus":0,"bps":10,"influence":"5.4","creativity":"15.8","threat":"2.0","ict_index":"2.3","ea_index":0,"open_play_crosses":0,"big_chances_created":1,"clearances_blocks_interceptions":0,"recoveries":3,"key_passes":1,"tackles":0,"winning_goals":0,"attempted_passes":16,"completed_passes":13,"penalties_conceded":0,"big_chances_missed":0,"errors_leading_to_goal":0,"errors_leading_to_goal_attempt":0,"tackled":0,"offside":0,"target_missed":0,"fouls":0,"dribbles":2,"element":419,"fixture":129,"opponent_team":13},{"id":7444,"kickoff_time":"2018-12-01T15:00:00Z","kickoff_time_formatted":"01 Dec 15:00","team_h_score":0,"team_a_score":3,"was_home":false,"round":14,"total_points":13,"value":62,"transfers_balance":-328,"selected":62668,"transfers_in":805,"transfers_out":1133,"loaned_in":0,"loaned_out":0,"minutes":90,"goals_scored":2,"assists":0,"clean_sheets":1,"goals_conceded":0,"own_goals":0,"penalties_saved":0,"penalties_missed":0,"yellow_cards":0,"red_cards":0,"saves":0,"bonus":3,"bps":49,"influence":"65.2","creativity":"6.3","threat":"42.0","ict_index":"11.4","ea_index":0,"open_play_crosses":0,"big_chances_created":0,"clearances_blocks_interceptions":1,"recoveries":3,"key_passes":0,"tackles":0,"winning_goals":1,"attempted_passes":26,"completed_passes":17,"penalties_conceded":0,"big_chances_missed":2,"errors_leading_to_goal":0,"errors_leading_to_goal_attempt":0,"tackled":1,"offside":0,"target_missed":2,"fouls":0,"dribbles":0,"element":419,"fixture":139,"opponent_team":15},{"id":8000,"kickoff_time":"2018-12-04T19:45:00Z","kickoff_time_formatted":"04 Dec 19:45","team_h_score":3,"team_a_score":1,"was_home":true,"round":15,"total_points":2,"value":62,"transfers_balance":49681,"selected":116574,"transfers_in":52048,"transfers_out":2367,"loaned_in":0,"loaned_out":0,"minutes":63,"goals_scored":0,"assists":0,"clean_sheets":1,"goals_conceded":0,"own_goals":0,"penalties_saved":0,"penalties_missed":0,"yellow_cards":0,"red_cards":0,"saves":0,"bonus":0,"bps":5,"influence":"0.0","creativity":"3.8","threat":"0.0","ict_index":"0.2","ea_index":0,"open_play_crosses":0,"big_chances_created":0,"clearances_blocks_interceptions":0,"recoveries":1,"key_passes":0,"tackles":0,"winning_goals":0,"attempted_passes":16,"completed_passes":7,"penalties_conceded":0,"big_chances_missed":0,"errors_leading_to_goal":0,"errors_leading_to_goal_attempt":0,"tackled":0,"offside":0,"target_missed":0,"fouls":1,"dribbles":0,"element":419,"fixture":147,"opponent_team":5},{"id":8558,"kickoff_time":"2018-12-08T15:00:00Z","kickoff_time_formatted":"08 Dec 15:00","team_h_score":3,"team_a_score":2,"was_home":true,"round":16,"total_points":9,"value":63,"transfers_balance":83433,"selected":201627,"transfers_in":94953,"transfers_out":11520,"loaned_in":0,"loaned_out":0,"minutes":74,"goals_scored":1,"assists":1,"clean_sheets":0,"goals_conceded":1,"own_goals":0,"penalties_saved":0,"penalties_missed":0,"yellow_cards":0,"red_cards":0,"saves":0,"bonus":0,"bps":34,"influence":"35.4","creativity":"2.0","threat":"56.0","ict_index":"9.3","ea_index":0,"open_play_crosses":0,"big_chances_created":0,"clearances_blocks_interceptions":0,"recoveries":5,"key_passes":0,"tackles":0,"winning_goals":0,"attempted_passes":24,"completed_passes":18,"penalties_conceded":0,"big_chances_missed":1,"errors_leading_to_goal":0,"errors_leading_to_goal_attempt":0,"tackled":1,"offside":2,"target_missed":1,"fouls":0,"dribbles":1,"element":419,"fixture":160,"opponent_team":7},{"id":9117,"kickoff_time":"2018-12-15T17:30:00Z","kickoff_time_formatted":"15 Dec 17:30","team_h_score":0,"team_a_score":2,"was_home":false,"round":17,"total_points":5,"value":64,"transfers_balance":228798,"selected":441052,"transfers_in":237946,"transfers_out":9148,"loaned_in":0,"loaned_out":0,"minutes":72,"goals_scored":0,"assists":1,"clean_sheets":1,"goals_conceded":0,"own_goals":0,"penalties_saved":0,"penalties_missed":0,"yellow_cards":0,"red_cards":0,"saves":0,"bonus":0,"bps":18,"influence":"18.2","creativity":"15.3","threat":"10.0","ict_index":"4.4","ea_index":0,"open_play_crosses":0,"big_chances_created":1,"clearances_blocks_interceptions":0,"recoveries":0,"key_passes":1,"tackles":0,"winning_goals":0,"attempted_passes":21,"completed_passes":16,"penalties_conceded":0,"big_chances_missed":0,"errors_leading_to_goal":0,"errors_leading_to_goal_attempt":0,"tackled":2,"offside":0,"target_missed":0,"fouls":0,"dribbles":1,"element":419,"fixture":163,"opponent_team":9},{"id":9679,"kickoff_time":"2018-12-22T15:00:00Z","kickoff_time_formatted":"22 Dec 15:00","team_h_score":0,"team_a_score":2,"was_home":true,"round":18,"total_points":2,"value":65,"transfers_balance":34714,"selected":469043,"transfers_in":59659,"transfers_out":24945,"loaned_in":0,"loaned_out":0,"minutes":74,"goals_scored":0,"assists":0,"clean_sheets":0,"goals_conceded":1,"own_goals":0,"penalties_saved":0,"penalties_missed":0,"yellow_cards":0,"red_cards":0,"saves":0,"bonus":0,"bps":0,"influence":"6.8","creativity":"0.6","threat":"56.0","ict_index":"6.3","ea_index":0,"open_play_crosses":0,"big_chances_created":0,"clearances_blocks_interceptions":1,"recoveries":0,"key_passes":0,"tackles":0,"winning_goals":0,"attempted_passes":15,"completed_passes":10,"penalties_conceded":0,"big_chances_missed":1,"errors_leading_to_goal":0,"errors_leading_to_goal_attempt":0,"tackled":2,"offside":1,"target_missed":0,"fouls":1,"dribbles":1,"element":419,"fixture":179,"opponent_team":18},{"id":10244,"kickoff_time":"2018-12-27T19:45:00Z","kickoff_time_formatted":"27 Dec 19:45","team_h_score":1,"team_a_score":2,"was_home":false,"round":19,"total_points":0,"value":64,"transfers_balance":-123011,"selected":342014,"transfers_in":13407,"transfers_out":136418,"loaned_in":0,"loaned_out":0,"minutes":0,"goals_scored":0,"assists":0,"clean_sheets":0,"goals_conceded":0,"own_goals":0,"penalties_saved":0,"penalties_missed":0,"yellow_cards":0,"red_cards":0,"saves":0,"bonus":0,"bps":0,"influence":"0.0","creativity":"0.0","threat":"0.0","ict_index":"0.0","ea_index":0,"open_play_crosses":0,"big_chances_created":0,"clearances_blocks_interceptions":0,"recoveries":0,"key_passes":0,"tackles":0,"winning_goals":0,"attempted_passes":0,"completed_passes":0,"penalties_conceded":0,"big_chances_missed":0,"errors_leading_to_goal":0,"errors_leading_to_goal_attempt":0,"tackled":0,"offside":0,"target_missed":0,"fouls":0,"dribbles":0,"element":419,"fixture":188,"opponent_team":16},{"id":10812,"kickoff_time":"2018-12-30T14:15:00Z","kickoff_time_formatted":"30 Dec 14:15","team_h_score":2,"team_a_score":0,"was_home":false,"round":20,"total_points":0,"value":63,"transfers_balance":-97656,"selected":245563,"transfers_in":2776,"transfers_out":100432,"loaned_in":0,"loaned_out":0,"minutes":0,"goals_scored":0,"assists":0,"clean_sheets":0,"goals_conceded":0,"own_goals":0,"penalties_saved":0,"penalties_missed":0,"yellow_cards":0,"red_cards":0,"saves":0,"bonus":0,"bps":0,"influence":"0.0","creativity":"0.0","threat":"0.0","ict_index":"0.0","ea_index":0,"open_play_crosses":0,"big_chances_created":0,"clearances_blocks_interceptions":0,"recoveries":0,"key_passes":0,"tackles":0,"winning_goals":0,"attempted_passes":0,"completed_passes":0,"penalties_conceded":0,"big_chances_missed":0,"errors_leading_to_goal":0,"errors_leading_to_goal_attempt":0,"tackled":0,"offside":0,"target_missed":0,"fouls":0,"dribbles":0,"element":419,"fixture":192,"opponent_team":4},{"id":11380,"kickoff_time":"2019-01-02T19:45:00Z","kickoff_time_formatted":"02 Jan 19:45","team_h_score":2,"team_a_score":2,"was_home":true,"round":21,"total_points":0,"value":62,"transfers_balance":-82027,"selected":166277,"transfers_in":519,"transfers_out":82546,"loaned_in":0,"loaned_out":0,"minutes":0,"goals_scored":0,"assists":0,"clean_sheets":0,"goals_conceded":0,"own_goals":0,"penalties_saved":0,"penalties_missed":0,"yellow_cards":0,"red_cards":0,"saves":0,"bonus":0,"bps":0,"influence":"0.0","creativity":"0.0","threat":"0.0","ict_index":"0.0","ea_index":0,"open_play_crosses":0,"big_chances_created":0,"clearances_blocks_interceptions":0,"recoveries":0,"key_passes":0,"tackles":0,"winning_goals":0,"attempted_passes":0,"completed_passes":0,"penalties_conceded":0,"big_chances_missed":0,"errors_leading_to_goal":0,"errors_leading_to_goal_attempt":0,"tackled":0,"offside":0,"target_missed":0,"fouls":0,"dribbles":0,"element":419,"fixture":209,"opponent_team":3},{"id":11950,"kickoff_time":"2019-01-12T12:30:00Z","kickoff_time_formatted":"12 Jan 12:30","team_h_score":1,"team_a_score":0,"was_home":true,"round":22,"total_points":0,"value":61,"transfers_balance":-58647,"selected":108767,"transfers_in":267,"transfers_out":58914,"loaned_in":0,"loaned_out":0,"minutes":0,"goals_scored":0,"assists":0,"clean_sheets":0,"goals_conceded":0,"own_goals":0,"penalties_saved":0,"penalties_missed":0,"yellow_cards":0,"red_cards":0,"saves":0,"bonus":0,"bps":0,"influence":"0.0","creativity":"0.0","threat":"0.0","ict_index":"0.0","ea_index":0,"open_play_crosses":0,"big_chances_created":0,"clearances_blocks_interceptions":0,"recoveries":0,"key_passes":0,"tackles":0,"winning_goals":0,"attempted_passes":0,"completed_passes":0,"penalties_conceded":0,"big_chances_missed":0,"errors_leading_to_goal":0,"errors_leading_to_goal_attempt":0,"tackled":0,"offside":0,"target_missed":0,"fouls":0,"dribbles":0,"element":419,"fixture":220,"opponent_team":1},{"id":12524,"kickoff_time":"2019-01-19T15:00:00Z","kickoff_time_formatted":"19 Jan 15:00","team_h_score":2,"team_a_score":0,"was_home":false,"round":23,"total_points":1,"value":61,"transfers_balance":-16271,"selected":93102,"transfers_in":629,"transfers_out":16900,"loaned_in":0,"loaned_out":0,"minutes":24,"goals_scored":0,"assists":0,"clean_sheets":0,"goals_conceded":1,"own_goals":0,"penalties_saved":0,"penalties_missed":0,"yellow_cards":0,"red_cards":0,"saves":0,"bonus":0,"bps":3,"influence":"3.2","creativity":"3.6","threat":"11.0","ict_index":"1.8","ea_index":0,"open_play_crosses":0,"big_chances_created":0,"clearances_blocks_interceptions":0,"recoveries":2,"key_passes":0,"tackles":0,"winning_goals":0,"attempted_passes":6,"completed_passes":4,"penalties_conceded":0,"big_chances_missed":0,"errors_leading_to_goal":0,"errors_leading_to_goal_attempt":0,"tackled":0,"offside":0,"target_missed":0,"fouls":0,"dribbles":0,"element":419,"fixture":222,"opponent_team":2},{"id":13103,"kickoff_time":"2019-01-29T19:45:00Z","kickoff_time_formatted":"29 Jan 19:45","team_h_score":3,"team_a_score":0,"was_home":false,"round":24,"total_points":1,"value":61,"transfers_balance":-3479,"selected":90247,"transfers_in":1755,"transfers_out":5234,"loaned_in":0,"loaned_out":0,"minutes":13,"goals_scored":0,"assists":0,"clean_sheets":0,"goals_conceded":2,"own_goals":0,"penalties_saved":0,"penalties_missed":0,"yellow_cards":0,"red_cards":0,"saves":0,"bonus":0,"bps":1,"influence":"5.0","creativity":"0.0","threat":"2.0","ict_index":"0.7","ea_index":0,"open_play_crosses":0,"big_chances_created":0,"clearances_blocks_interceptions":1,"recoveries":0,"key_passes":0,"tackles":0,"winning_goals":0,"attempted_passes":2,"completed_passes":2,"penalties_conceded":0,"big_chances_missed":0,"errors_leading_to_goal":0,"errors_leading_to_goal_attempt":0,"tackled":2,"offside":0,"target_missed":0,"fouls":0,"dribbles":0,"element":419,"fixture":236,"opponent_team":20},{"id":13733,"kickoff_time":"2019-02-04T20:00:00Z","kickoff_time_formatted":"04 Feb 20:00","team_h_score":1,"team_a_score":1,"was_home":true,"round":25,"total_points":1,"value":61,"transfers_balance":-3172,"selected":87055,"transfers_in":716,"transfers_out":3888,"loaned_in":0,"loaned_out":0,"minutes":78,"goals_scored":0,"assists":0,"clean_sheets":0,"goals_conceded":1,"own_goals":0,"penalties_saved":0,"penalties_missed":0,"yellow_cards":1,"red_cards":0,"saves":0,"bonus":0,"bps":-2,"influence":"0.0","creativity":"1.9","threat":"35.0","ict_index":"3.3","ea_index":0,"open_play_crosses":0,"big_chances_created":0,"clearances_blocks_interceptions":2,"recoveries":0,"key_passes":0,"tackles":0,"winning_goals":0,"attempted_passes":10,"completed_passes":7,"penalties_conceded":0,"big_chances_missed":0,"errors_leading_to_goal":0,"errors_leading_to_goal_attempt":0,"tackled":0,"offside":1,"target_missed":2,"fouls":3,"dribbles":0,"element":419,"fixture":250,"opponent_team":12},{"id":14340,"kickoff_time":"2019-02-09T15:00:00Z","kickoff_time_formatted":"09 Feb 15:00","team_h_score":1,"team_a_score":1,"was_home":false,"round":26,"total_points":2,"value":61,"transfers_balance":-488,"selected":87204,"transfers_in":2969,"transfers_out":3457,"loaned_in":0,"loaned_out":0,"minutes":67,"goals_scored":0,"assists":0,"clean_sheets":1,"goals_conceded":0,"own_goals":0,"penalties_saved":0,"penalties_missed":0,"yellow_cards":0,"red_cards":0,"saves":0,"bonus":0,"bps":2,"influence":"2.6","creativity":"2.4","threat":"31.0","ict_index":"3.6","ea_index":0,"open_play_crosses":0,"big_chances_created":0,"clearances_blocks_interceptions":0,"recoveries":1,"key_passes":0,"tackles":0,"winning_goals":0,"attempted_passes":13,"completed_passes":11,"penalties_conceded":0,"big_chances_missed":0,"errors_leading_to_goal":0,"errors_leading_to_goal_attempt":0,"tackled":4,"offside":0,"target_missed":0,"fouls":0,"dribbles":0,"element":419,"fixture":252,"opponent_team":7},{"id":14848,"kickoff_time":"2019-02-22T19:45:00Z","kickoff_time_formatted":"22 Feb 19:45","team_h_score":3,"team_a_score":1,"was_home":true,"round":27,"total_points":9,"value":61,"transfers_balance":1062,"selected":89263,"transfers_in":3804,"transfers_out":2742,"loaned_in":0,"loaned_out":0,"minutes":63,"goals_scored":1,"assists":0,"clean_sheets":0,"goals_conceded":1,"own_goals":0,"penalties_saved":0,"penalties_missed":0,"yellow_cards":0,"red_cards":0,"saves":0,"bonus":3,"bps":30,"influence":"32.2","creativity":"7.8","threat":"59.0","ict_index":"9.9","ea_index":0,"open_play_crosses":0,"big_chances_created":0,"clearances_blocks_interceptions":1,"recoveries":1,"key_passes":0,"tackles":0,"winning_goals":0,"attempted_passes":16,"completed_passes":9,"penalties_conceded":0,"big_chances_missed":0,"errors_leading_to_goal":0,"errors_leading_to_goal_attempt":0,"tackled":0,"offside":0,"target_missed":1,"fouls":0,"dribbles":1,"element":419,"fixture":270,"opponent_team":9},{"id":15424,"kickoff_time":"2019-02-27T20:00:00Z","kickoff_time_formatted":"27 Feb 20:00","team_h_score":1,"team_a_score":0,"was_home":false,"round":28,"total_points":0,"value":61,"transfers_balance":880,"selected":89889,"transfers_in":2763,"transfers_out":1883,"loaned_in":0,"loaned_out":0,"minutes":0,"goals_scored":0,"assists":0,"clean_sheets":0,"goals_conceded":0,"own_goals":0,"penalties_saved":0,"penalties_missed":0,"yellow_cards":0,"red_cards":0,"saves":0,"bonus":0,"bps":0,"influence":"0.0","creativity":"0.0","threat":"0.0","ict_index":"0.0","ea_index":0,"open_play_crosses":0,"big_chances_created":0,"clearances_blocks_interceptions":0,"recoveries":0,"key_passes":0,"tackles":0,"winning_goals":0,"attempted_passes":0,"completed_passes":0,"penalties_conceded":0,"big_chances_missed":0,"errors_leading_to_goal":0,"errors_leading_to_goal_attempt":0,"tackled":0,"offside":0,"target_missed":0,"fouls":0,"dribbles":0,"element":419,"fixture":278,"opponent_team":13},{"id":16029,"kickoff_time":"2019-03-02T17:30:00Z","kickoff_time_formatted":"02 Mar 17:30","team_h_score":2,"team_a_score":0,"was_home":true,"round":29,"total_points":5,"value":61,"transfers_balance":4153,"selected":94272,"transfers_in":6399,"transfers_out":2246,"loaned_in":0,"loaned_out":0,"minutes":69,"goals_scored":0,"assists":1,"clean_sheets":1,"goals_conceded":0,"own_goals":0,"penalties_saved":0,"penalties_missed":0,"yellow_cards":0,"red_cards":0,"saves":0,"bonus":0,"bps":9,"influence":"0.0","creativity":"1.6","threat":"53.0","ict_index":"5.4","ea_index":0,"open_play_crosses":0,"big_chances_created":0,"clearances_blocks_interceptions":0,"recoveries":2,"key_passes":0,"tackles":0,"winning_goals":0,"attempted_passes":15,"completed_passes":11,"penalties_conceded":0,"big_chances_missed":1,"errors_leading_to_goal":0,"errors_leading_to_goal_attempt":0,"tackled":0,"offside":1,"target_missed":2,"fouls":0,"dribbles":0,"element":419,"fixture":289,"opponent_team":15},{"id":16635,"kickoff_time":"2019-03-09T15:00:00Z","kickoff_time_formatted":"09 Mar 15:00","team_h_score":2,"team_a_score":0,"was_home":false,"round":30,"total_points":1,"value":61,"transfers_balance":13322,"selected":108099,"transfers_in":16005,"transfers_out":2683,"loaned_in":0,"loaned_out":0,"minutes":90,"goals_scored":0,"assists":0,"clean_sheets":0,"goals_conceded":2,"own_goals":0,"penalties_saved":0,"penalties_missed":0,"yellow_cards":1,"red_cards":0,"saves":0,"bonus":0,"bps":0,"influence":"1.0","creativity":"3.4","threat":"0.0","ict_index":"0.4","ea_index":0,"open_play_crosses":0,"big_chances_created":0,"clearances_blocks_interceptions":1,"recoveries":1,"key_passes":0,"tackles":0,"winning_goals":0,"attempted_passes":23,"completed_passes":16,"penalties_conceded":0,"big_chances_missed":0,"errors_leading_to_goal":0,"errors_leading_to_goal_attempt":0,"tackled":1,"offside":1,"target_missed":0,"fouls":2,"dribbles":1,"element":419,"fixture":292,"opponent_team":5},{"id":17037,"kickoff_time":"2019-03-16T15:00:00Z","kickoff_time_formatted":"16 Mar 15:00","team_h_score":4,"team_a_score":3,"was_home":true,"round":31,"total_points":12,"value":61,"transfers_balance":15174,"selected":149754,"transfers_in":19575,"transfers_out":4401,"loaned_in":0,"loaned_out":0,"minutes":45,"goals_scored":2,"assists":0,"clean_sheets":0,"goals_conceded":1,"own_goals":0,"penalties_saved":0,"penalties_missed":0,"yellow_cards":0,"red_cards":0,"saves":0,"bonus":3,"bps":53,"influence":"66.8","creativity":"2.5","threat":"36.0","ict_index":"10.5","ea_index":0,"open_play_crosses":0,"big_chances_created":0,"clearances_blocks_interceptions":0,"recoveries":1,"key_passes":0,"tackles":0,"winning_goals":1,"attempted_passes":16,"completed_passes":13,"penalties_conceded":0,"big_chances_missed":0,"errors_leading_to_goal":0,"errors_leading_to_goal_attempt":0,"tackled":1,"offside":0,"target_missed":0,"fouls":0,"dribbles":0,"element":419,"fixture":309,"opponent_team":10},{"id":17745,"kickoff_time":"2019-03-30T17:30:00Z","kickoff_time_formatted":"30 Mar 17:30","team_h_score":0,"team_a_score":2,"was_home":true,"round":32,"total_points":1,"value":61,"transfers_balance":-4925,"selected":116662,"transfers_in":10842,"transfers_out":15767,"loaned_in":0,"loaned_out":0,"minutes":45,"goals_scored":0,"assists":0,"clean_sheets":0,"goals_conceded":0,"own_goals":0,"penalties_saved":0,"penalties_missed":0,"yellow_cards":0,"red_cards":0,"saves":0,"bonus":0,"bps":1,"influence":"3.2","creativity":"0.1","threat":"0.0","ict_index":"0.3","ea_index":0,"open_play_crosses":0,"big_chances_created":0,"clearances_blocks_interceptions":0,"recoveries":1,"key_passes":0,"tackles":0,"winning_goals":0,"attempted_passes":4,"completed_passes":2,"penalties_conceded":0,"big_chances_missed":0,"errors_leading_to_goal":0,"errors_leading_to_goal_attempt":0,"tackled":1,"offside":0,"target_missed":0,"fouls":1,"dribbles":0,"element":419,"fixture":320,"opponent_team":8},{"id":18298,"kickoff_time":"2019-04-08T19:00:00Z","kickoff_time_formatted":"08 Apr 20:00","team_h_score":2,"team_a_score":0,"was_home":false,"round":33,"total_points":1,"value":61,"transfers_balance":-4463,"selected":114833,"transfers_in":2923,"transfers_out":7386,"loaned_in":0,"loaned_out":0,"minutes":45,"goals_scored":0,"assists":0,"clean_sheets":0,"goals_conceded":1,"own_goals":0,"penalties_saved":0,"penalties_missed":0,"yellow_cards":0,"red_cards":0,"saves":0,"bonus":0,"bps":5,"influence":"1.0","creativity":"0.2","threat":"0.0","ict_index":"0.1","ea_index":0,"open_play_crosses":0,"big_chances_created":0,"clearances_blocks_interceptions":0,"recoveries":1,"key_passes":0,"tackles":0,"winning_goals":0,"attempted_passes":10,"completed_passes":6,"penalties_conceded":0,"big_chances_missed":0,"errors_leading_to_goal":0,"errors_leading_to_goal_attempt":0,"tackled":0,"offside":0,"target_missed":0,"fouls":0,"dribbles":2,"element":419,"fixture":322,"opponent_team":6},{"id":18870,"kickoff_time":"2019-04-13T16:30:00Z","kickoff_time_formatted":"13 Apr 17:30","team_h_score":2,"team_a_score":1,"was_home":false,"round":34,"total_points":2,"value":61,"transfers_balance":-9215,"selected":105790,"transfers_in":896,"transfers_out":10111,"loaned_in":0,"loaned_out":0,"minutes":72,"goals_scored":0,"assists":0,"clean_sheets":0,"goals_conceded":1,"own_goals":0,"penalties_saved":0,"penalties_missed":0,"yellow_cards":0,"red_cards":0,"saves":0,"bonus":0,"bps":6,"influence":"3.4","creativity":"12.1","threat":"6.0","ict_index":"2.2","ea_index":0,"open_play_crosses":0,"big_chances_created":0,"clearances_blocks_interceptions":0,"recoveries":4,"key_passes":1,"tackles":0,"winning_goals":0,"attempted_passes":15,"completed_passes":11,"penalties_conceded":0,"big_chances_missed":0,"errors_leading_to_goal":0,"errors_leading_to_goal_attempt":0,"tackled":2,"offside":2,"target_missed":0,"fouls":0,"dribbles":2,"element":419,"fixture":337,"opponent_team":14},{"id":19659,"kickoff_time":"2019-04-20T14:00:00Z","kickoff_time_formatted":"20 Apr 15:00","team_h_score":2,"team_a_score":2,"was_home":true,"round":35,"total_points":0,"value":61,"transfers_balance":-7569,"selected":98106,"transfers_in":1178,"transfers_out":8747,"loaned_in":0,"loaned_out":0,"minutes":0,"goals_scored":0,"assists":0,"clean_sheets":0,"goals_conceded":0,"own_goals":0,"penalties_saved":0,"penalties_missed":0,"yellow_cards":0,"red_cards":0,"saves":0,"bonus":0,"bps":0,"influence":"0.0","creativity":"0.0","threat":"0.0","ict_index":"0.0","ea_index":0,"open_play_crosses":0,"big_chances_created":0,"clearances_blocks_interceptions":0,"recoveries":0,"key_passes":0,"tackles":0,"winning_goals":0,"attempted_passes":0,"completed_passes":0,"penalties_conceded":0,"big_chances_missed":0,"errors_leading_to_goal":0,"errors_leading_to_goal_attempt":0,"tackled":0,"offside":0,"target_missed":0,"fouls":0,"dribbles":0,"element":419,"fixture":349,"opponent_team":11},{"id":20355,"kickoff_time":"2019-04-27T11:30:00Z","kickoff_time_formatted":"27 Apr 12:30","team_h_score":0,"team_a_score":1,"was_home":false,"round":36,"total_points":0,"value":61,"transfers_balance":-5031,"selected":93401,"transfers_in":73,"transfers_out":5104,"loaned_in":0,"loaned_out":0,"minutes":0,"goals_scored":0,"assists":0,"clean_sheets":0,"goals_conceded":0,"own_goals":0,"penalties_saved":0,"penalties_missed":0,"yellow_cards":0,"red_cards":0,"saves":0,"bonus":0,"bps":0,"influence":"0.0","creativity":"0.0","threat":"0.0","ict_index":"0.0","ea_index":0,"open_play_crosses":0,"big_chances_created":0,"clearances_blocks_interceptions":0,"recoveries":0,"key_passes":0,"tackles":0,"winning_goals":0,"attempted_passes":0,"completed_passes":0,"penalties_conceded":0,"big_chances_missed":0,"errors_leading_to_goal":0,"errors_leading_to_goal_attempt":0,"tackled":0,"offside":0,"target_missed":0,"fouls":0,"dribbles":0,"element":419,"fixture":359,"opponent_team":17},{"id":20970,"kickoff_time":"2019-05-04T14:00:00Z","kickoff_time_formatted":"04 May 15:00","team_h_score":3,"team_a_score":0,"was_home":true,"round":37,"total_points":0,"value":61,"transfers_balance":371,"selected":94074,"transfers_in":2495,"transfers_out":2124,"loaned_in":0,"loaned_out":0,"minutes":0,"goals_scored":0,"assists":0,"clean_sheets":0,"goals_conceded":0,"own_goals":0,"penalties_saved":0,"penalties_missed":0,"yellow_cards":0,"red_cards":0,"saves":0,"bonus":0,"bps":0,"influence":"0.0","creativity":"0.0","threat":"0.0","ict_index":"0.0","ea_index":0,"open_play_crosses":0,"big_chances_created":0,"clearances_blocks_interceptions":0,"recoveries":0,"key_passes":0,"tackles":0,"winning_goals":0,"attempted_passes":0,"completed_passes":0,"penalties_conceded":0,"big_chances_missed":0,"errors_leading_to_goal":0,"errors_leading_to_goal_attempt":0,"tackled":0,"offside":0,"target_missed":0,"fouls":0,"dribbles":0,"element":419,"fixture":369,"opponent_team":16},{"id":21586,"kickoff_time":"2019-05-12T14:00:00Z","kickoff_time_formatted":"12 May 15:00","team_h_score":1,"team_a_score":4,"was_home":false,"round":38,"total_points":0,"value":61,"transfers_balance":-2237,"selected":91700,"transfers_in":505,"transfers_out":2742,"loaned_in":0,"loaned_out":0,"minutes":0,"goals_scored":0,"assists":0,"clean_sheets":0,"goals_conceded":0,"own_goals":0,"penalties_saved":0,"penalties_missed":0,"yellow_cards":0,"red_cards":0,"saves":0,"bonus":0,"bps":0,"influence":"0.0","creativity":"0.0","threat":"0.0","ict_index":"0.0","ea_index":0,"open_play_crosses":0,"big_chances_created":0,"clearances_blocks_interceptions":0,"recoveries":0,"key_passes":0,"tackles":0,"winning_goals":0,"attempted_passes":0,"completed_passes":0,"penalties_conceded":0,"big_chances_missed":0,"errors_leading_to_goal":0,"errors_leading_to_goal_attempt":0,"tackled":0,"offside":0,"target_missed":0,"fouls":0,"dribbles":0,"element":419,"fixture":380,"opponent_team":18}]}