{"history_past":[],"fixtures_summary":[],"explain":[{"explain":{"minutes":{"points":0,"name":"Minutes played","value":0}},"fixture":{"id":374,"kickoff_time_formatted":"12 May 15:00","started":true,"event_day":1,"deadline_time":"2019-05-12T13:00:00Z","deadline_time_formatted":"12 May 14:00","stats":[{"goals_scored":{"a":[{"value":1,"element":318},{"value":1,"element":326},{"value":1,"element":482},{"value":1,"element":493}],"h":[]}},{"assists":{"a":[{"value":2,"element":317},{"value":1,"element":320}],"h":[]}},{"own_goals":{"a":[],"h":[]}},{"penalties_saved":{"a":[],"h":[]}},{"penalties_missed":{"a":[],"h":[]}},{"yellow_cards":{"a":[],"h":[{"value":1,"element":510}]}},{"red_cards":{"a":[],"h":[]}},{"saves":{"a":[{"value":2,"element":309}],"h":[{"value":2,"element":509}]}},{"bonus":{"a":[{"value":3,"element":482},{"value":2,"element":318},{"value":1,"element":326}],"h":[]}},{"bps":{"a":[{"value":37,"element":482},{"value":34,"element":318},{"value":33,"element":326},{"value":30,"element":317},{"value":28,"element":312},{"value":27,"element":309},{"value":27,"element":313},{"value":26,"element":493},{"value":14,"element":319},{"value":14,"element":320},{"value":10,"element":323},{"value":5,"element":516},{"value":3,"element":488},{"value":2,"element":458}],"h":[{"value":19,"element":455},{"value":16,"element":182},{"value":15,"element":9},{"value":15,"element":487},{"value":14,"element":186},{"value":14,"element":512},{"value":13,"element":510},{"value":8,"element":184},{"value":8,"element":509},{"value":6,"element":460},{"value":4,"element":610},{"value":3,"element":187},{"value":3,"element":480}]}}],"code":987965,"kickoff_time":"2019-05-12T14:00:00Z","team_h_score":0,"team_a_score":4,"finished":true,"minutes":90,"provisional_start_time":false,"finished_provisional":true,"event":38,"team_a":15,"team_h":9}}],"history_summary":[{"id":21789,"kickoff_time":"2019-05-12T14:00:00Z","kickoff_time_formatted":"12 May 15:00","team_h_score":0,"team_a_score":4,"was_home":false,"round":38,"total_points":0,"value":45,"transfers_balance":0,"selected":0,"transfers_in":0,"transfers_out":0,"loaned_in":0,"loaned_out":0,"minutes":0,"goals_scored":0,"assists":0,"clean_sheets":0,"goals_conceded":0,"own_goals":0,"penalties_saved":0,"penalties_missed":0,"yellow_cards":0,"red_cards":0,"saves":0,"bonus":0,"bps":0,"influence":"0.0","creativity":"0.0","threat":"0.0","ict_index":"0.0","ea_index":0,"open_play_crosses":0,"big_chances_created":0,"clearances_blocks_interceptions":0,"recoveries":0,"key_passes":0,"tackles":0,"winning_goals":0,"attempted_passes":0,"completed_passes":0,"penalties_conceded":0,"big_chances_missed":0,"errors_leading_to_goal":0,"errors_leading_to_goal_attempt":0,"tackled":0,"offside":0,"target_missed":0,"fouls":0,"dribbles":0,"element":622,"fixture":374,"opponent_team":9}],"fixtures":[],"history":[{"id":21789,"kickoff_time":"2019-05-12T14:00:00Z","kickoff_time_formatted":"12 May 15:00","team_h_score":0,"team_a_score":4,"was_home":false,"round":38,"total_points":0,"value":45,"transfers_balance":0,"selected":0,"transfers_in":0,"transfers_out":0,"loaned_in":0,"loaned_out":0,"minutes":0,"goals_scored":0,"assists":0,"clean_sheets":0,"goals_conceded":0,"own_goals":0,"penalties_saved":0,"penalties_missed":0,"yellow_cards":0,"red_cards":0,"saves":0,"bonus":0,"bps":0,"influence":"0.0","creativity":"0.0","threat":"0.0","ict_index":"0.0","ea_index":0,"open_play_crosses":0,"big_chances_created":0,"clearances_blocks_interceptions":0,"recoveries":0,"key_passes":0,"tackles":0,"winning_goals":0,"attempted_passes":0,"completed_passes":0,"penalties_conceded":0,"big_chances_missed":0,"errors_leading_to_goal":0,"errors_leading_to_goal_attempt":0,"tackled":0,"offside":0,"target_missed":0,"fouls":0,"dribbles":0,"element":622,"fixture":374,"opponent_team":9}]}